{
 	"PracticeID" : "{785FE83C-D809-40b5-9833-54FEFD9C3999}", 
	 "AreaID" : "RP1",
	 "Points": 
	[
		{"Index":1, "x" : 187.246, "y" : 16.387, "z" : 0, "Brake" : 0, "Clutch" : 0, "Accelerat" : 0, "CarDir" :182.26, "SteelAng" : 0, "ErrContent" : ""},
		{"Index":2, "x" : 187.246, "y" : 16.387, "z" : 0, "Brake" : 0, "Clutch" : 0, "Accelerat" : 0, "CarDir" :182.26, "SteelAng" : 0, "ErrContent" : ""},
		{"Index":3, "x" : 187.246, "y" : 16.387, "z" : 0, "Brake" : 0, "Clutch" : 0, "Accelerat" : 0, "CarDir" :182.26, "SteelAng" : 0, "ErrContent" : ""},
		{"Index":4, "x" : 187.246, "y" : 16.387, "z" : 0, "Brake" : 0, "Clutch" : 0, "Accelerat" : 0, "CarDir" :182.26, "SteelAng" : 0, "ErrContent" : ""},
		{"Index":5, "x" : 187.246, "y" : 16.387, "z" : 0, "Brake" : 0, "Clutch" : 0, "Accelerat" : 0, "CarDir" :182.26, "SteelAng" : 0, "ErrContent" : ""},
		{"Index":6, "x" : 187.246, "y" : 16.387, "z" : 0, "Brake" : 0, "Clutch" : 0, "Accelerat" : 0, "CarDir" :182.26, "SteelAng" : 0, "ErrContent" : ""},
		{"Index":7, "x" : 187.246, "y" : 16.387, "z" : 0, "Brake" : 0, "Clutch" : 0, "Accelerat" : 0, "CarDir" :182.26, "SteelAng" : 0, "ErrContent" : ""},
		{"Index":8, "x" : 187.246, "y" : 16.387, "z" : 0, "Brake" : 0, "Clutch" : 0, "Accelerat" : 0, "CarDir" :182.26, "SteelAng" : 0, "ErrContent" : ""},
		{"Index":9, "x" : 187.246, "y" : 16.387, "z" : 0, "Brake" : 0, "Clutch" : 0, "Accelerat" : 0, "CarDir" :182.26, "SteelAng" : 0, "ErrContent" : ""},
		{"Index":10, "x" : 187.246, "y" : 16.387, "z" : 0, "Brake" : 0, "Clutch" : 0, "Accelerat" : 0, "CarDir" :182.26, "SteelAng" : 0, "ErrContent" : ""},
		{"Index":11, "x" : 187.246, "y" : 16.387, "z" : 0, "Brake" : 0, "Clutch" : 0, "Accelerat" : 0, "CarDir" :182.26, "SteelAng" : 0, "ErrContent" : ""},
		{"Index":12, "x" : 187.246, "y" : 16.387, "z" : 0, "Brake" : 0, "Clutch" : 0, "Accelerat" : 0, "CarDir" :182.26, "SteelAng" : 0, "ErrContent" : ""},
		{"Index":13, "x" : 187.246, "y" : 16.387, "z" : 0, "Brake" : 0, "Clutch" : 0, "Accelerat" : 0, "CarDir" :182.26, "SteelAng" : 0, "ErrContent" : ""},
		{"Index":14, "x" : 187.246, "y" : 16.387, "z" : 0, "Brake" : 0, "Clutch" : 0, "Accelerat" : 0, "CarDir" :182.26, "SteelAng" : 0, "ErrContent" : ""},
		{"Index":15, "x" : 187.246, "y" : 16.387, "z" : 0, "Brake" : 0, "Clutch" : 0, "Accelerat" : 0, "CarDir" :182.26, "SteelAng" : 0, "ErrContent" : ""},
		{"Index":16, "x" : 187.246, "y" : 16.387, "z" : 0, "Brake" : 0, "Clutch" : 0, "Accelerat" : 0, "CarDir" :182.26, "SteelAng" : 0, "ErrContent" : ""},
		{"Index":17, "x" : 187.246, "y" : 16.387, "z" : 0, "Brake" : 0, "Clutch" : 0, "Accelerat" : 0, "CarDir" :182.26, "SteelAng" : 0, "ErrContent" : ""},
		{"Index":18, "x" : 187.246, "y" : 16.387, "z" : 0, "Brake" : 0, "Clutch" : 0, "Accelerat" : 0, "CarDir" :182.26, "SteelAng" : 0, "ErrContent" : ""},
		{"Index":19, "x" : 187.246, "y" : 16.387, "z" : 0, "Brake" : 0, "Clutch" : 0, "Accelerat" : 0, "CarDir" :182.26, "SteelAng" : 0, "ErrContent" : ""},
		{"Index":20, "x" : 187.246, "y" : 16.387, "z" : 0, "Brake" : 0, "Clutch" : 0, "Accelerat" : 0, "CarDir" :182.26, "SteelAng" : 0, "ErrContent" : ""},
		{"Index":21, "x" : 187.246, "y" : 16.387, "z" : 0, "Brake" : 0, "Clutch" : 0, "Accelerat" : 0, "CarDir" :182.26, "SteelAng" : 0, "ErrContent" : ""},
		{"Index":22, "x" : 187.246, "y" : 16.387, "z" : 0, "Brake" : 0, "Clutch" : 0, "Accelerat" : 0, "CarDir" :182.26, "SteelAng" : 0, "ErrContent" : ""},
		{"Index":23, "x" : 187.246, "y" : 16.387, "z" : 0, "Brake" : 0, "Clutch" : 0, "Accelerat" : 0, "CarDir" :182.26, "SteelAng" : 0, "ErrContent" : ""},
		{"Index":24, "x" : 187.246, "y" : 16.387, "z" : 0, "Brake" : 0, "Clutch" : 0, "Accelerat" : 0, "CarDir" :182.26, "SteelAng" : 0, "ErrContent" : ""},
		{"Index":25, "x" : 187.246, "y" : 16.387, "z" : 0, "Brake" : 0, "Clutch" : 0, "Accelerat" : 0, "CarDir" :182.26, "SteelAng" : 0, "ErrContent" : ""},
		{"Index":26, "x" : 187.246, "y" : 16.387, "z" : 0, "Brake" : 0, "Clutch" : 0, "Accelerat" : 0, "CarDir" :182.26, "SteelAng" : 0, "ErrContent" : ""},
		{"Index":27, "x" : 187.246, "y" : 16.387, "z" : 0, "Brake" : 0, "Clutch" : 0, "Accelerat" : 0, "CarDir" :182.26, "SteelAng" : 0, "ErrContent" : ""},
		{"Index":28, "x" : 187.246, "y" : 16.387, "z" : 0, "Brake" : 0, "Clutch" : 0, "Accelerat" : 0, "CarDir" :182.26, "SteelAng" : 0, "ErrContent" : ""},
		{"Index":29, "x" : 187.246, "y" : 16.387, "z" : 0, "Brake" : 0, "Clutch" : 0, "Accelerat" : 0, "CarDir" :182.26, "SteelAng" : 0, "ErrContent" : ""},
		{"Index":30, "x" : 187.246, "y" : 16.387, "z" : 0, "Brake" : 0, "Clutch" : 0, "Accelerat" : 0, "CarDir" :182.26, "SteelAng" : 0, "ErrContent" : ""},
		{"Index":31, "x" : 187.246, "y" : 16.387, "z" : 0, "Brake" : 0, "Clutch" : 0, "Accelerat" : 0, "CarDir" :182.26, "SteelAng" : 0, "ErrContent" : ""},
		{"Index":32, "x" : 187.246, "y" : 16.387, "z" : 0, "Brake" : 0, "Clutch" : 0, "Accelerat" : 0, "CarDir" :182.26, "SteelAng" : 0, "ErrContent" : ""},
		{"Index":33, "x" : 187.246, "y" : 16.387, "z" : 0, "Brake" : 0, "Clutch" : 0, "Accelerat" : 0, "CarDir" :182.26, "SteelAng" : 0, "ErrContent" : ""},
		{"Index":34, "x" : 187.246, "y" : 16.387, "z" : 0, "Brake" : 0, "Clutch" : 0, "Accelerat" : 0, "CarDir" :182.26, "SteelAng" : 0, "ErrContent" : ""},
		{"Index":35, "x" : 187.246, "y" : 16.387, "z" : 0, "Brake" : 0, "Clutch" : 0, "Accelerat" : 0, "CarDir" :182.26, "SteelAng" : 0, "ErrContent" : ""},
		{"Index":36, "x" : 187.246, "y" : 16.387, "z" : 0, "Brake" : 0, "Clutch" : 0, "Accelerat" : 0, "CarDir" :182.26, "SteelAng" : 0, "ErrContent" : ""},
		{"Index":37, "x" : 187.246, "y" : 16.387, "z" : 0, "Brake" : 0, "Clutch" : 0, "Accelerat" : 0, "CarDir" :182.26, "SteelAng" : 0, "ErrContent" : ""},
		{"Index":38, "x" : 187.246, "y" : 16.387, "z" : 0, "Brake" : 0, "Clutch" : 0, "Accelerat" : 0, "CarDir" :182.26, "SteelAng" : 0, "ErrContent" : ""},
		{"Index":39, "x" : 187.246, "y" : 16.387, "z" : 0, "Brake" : 0, "Clutch" : 0, "Accelerat" : 0, "CarDir" :182.26, "SteelAng" : 0, "ErrContent" : ""},
		{"Index":40, "x" : 187.246, "y" : 16.387, "z" : 0, "Brake" : 0, "Clutch" : 0, "Accelerat" : 0, "CarDir" :182.26, "SteelAng" : 0, "ErrContent" : ""},
		{"Index":41, "x" : 187.246, "y" : 16.387, "z" : 0, "Brake" : 0, "Clutch" : 0, "Accelerat" : 0, "CarDir" :182.26, "SteelAng" : 0, "ErrContent" : ""},
		{"Index":42, "x" : 187.246, "y" : 16.387, "z" : 0, "Brake" : 0, "Clutch" : 0, "Accelerat" : 0, "CarDir" :182.26, "SteelAng" : 0, "ErrContent" : ""},
		{"Index":43, "x" : 187.246, "y" : 16.387, "z" : 0, "Brake" : 0, "Clutch" : 0, "Accelerat" : 0, "CarDir" :182.26, "SteelAng" : 0, "ErrContent" : ""},
		{"Index":44, "x" : 187.246, "y" : 16.387, "z" : 0, "Brake" : 0, "Clutch" : 0, "Accelerat" : 0, "CarDir" :182.26, "SteelAng" : 0, "ErrContent" : ""},
		{"Index":45, "x" : 187.246, "y" : 16.387, "z" : 0, "Brake" : 0, "Clutch" : 0, "Accelerat" : 0, "CarDir" :182.26, "SteelAng" : 0, "ErrContent" : ""},
		{"Index":46, "x" : 187.246, "y" : 16.387, "z" : 0, "Brake" : 0, "Clutch" : 0, "Accelerat" : 0, "CarDir" :182.26, "SteelAng" : 0, "ErrContent" : ""},
		{"Index":47, "x" : 187.246, "y" : 16.387, "z" : 0, "Brake" : 0, "Clutch" : 0, "Accelerat" : 0, "CarDir" :182.26, "SteelAng" : 0, "ErrContent" : ""},
		{"Index":48, "x" : 187.246, "y" : 16.387, "z" : 0, "Brake" : 0, "Clutch" : 0, "Accelerat" : 0, "CarDir" :182.26, "SteelAng" : 0, "ErrContent" : ""},
		{"Index":49, "x" : 187.246, "y" : 16.387, "z" : 0, "Brake" : 0, "Clutch" : 0, "Accelerat" : 0, "CarDir" :182.26, "SteelAng" : 0, "ErrContent" : ""},
		{"Index":50, "x" : 187.246, "y" : 16.387, "z" : 0, "Brake" : 0, "Clutch" : 0, "Accelerat" : 0, "CarDir" :182.26, "SteelAng" : 0, "ErrContent" : ""},
		{"Index":51, "x" : 187.246, "y" : 16.387, "z" : 0, "Brake" : 0, "Clutch" : 0, "Accelerat" : 0, "CarDir" :182.26, "SteelAng" : 0, "ErrContent" : ""},
		{"Index":52, "x" : 187.246, "y" : 16.387, "z" : 0, "Brake" : 0, "Clutch" : 0, "Accelerat" : 0, "CarDir" :182.26, "SteelAng" : 0, "ErrContent" : ""},
		{"Index":53, "x" : 187.246, "y" : 16.387, "z" : 0, "Brake" : 0, "Clutch" : 0, "Accelerat" : 0, "CarDir" :182.26, "SteelAng" : 0, "ErrContent" : ""},
		{"Index":54, "x" : 187.246, "y" : 16.387, "z" : 0, "Brake" : 0, "Clutch" : 0, "Accelerat" : 0, "CarDir" :182.26, "SteelAng" : 0, "ErrContent" : ""},
		{"Index":55, "x" : 187.246, "y" : 16.387, "z" : 0, "Brake" : 0, "Clutch" : 0, "Accelerat" : 0, "CarDir" :182.26, "SteelAng" : 0, "ErrContent" : ""},
		{"Index":56, "x" : 187.246, "y" : 16.387, "z" : 0, "Brake" : 0, "Clutch" : 0, "Accelerat" : 0, "CarDir" :182.26, "SteelAng" : 0, "ErrContent" : ""},
		{"Index":57, "x" : 187.246, "y" : 16.387, "z" : 0, "Brake" : 0, "Clutch" : 0, "Accelerat" : 0, "CarDir" :182.26, "SteelAng" : 0, "ErrContent" : ""},
		{"Index":58, "x" : 187.246, "y" : 16.387, "z" : 0, "Brake" : 0, "Clutch" : 0, "Accelerat" : 0, "CarDir" :182.26, "SteelAng" : 0, "ErrContent" : ""},
		{"Index":59, "x" : 187.246, "y" : 16.387, "z" : 0, "Brake" : 0, "Clutch" : 0, "Accelerat" : 0, "CarDir" :182.26, "SteelAng" : 0, "ErrContent" : ""},
		{"Index":60, "x" : 187.246, "y" : 16.387, "z" : 0, "Brake" : 0, "Clutch" : 0, "Accelerat" : 0, "CarDir" :182.26, "SteelAng" : 0, "ErrContent" : ""},
		{"Index":61, "x" : 187.246, "y" : 16.387, "z" : 0, "Brake" : 0, "Clutch" : 0, "Accelerat" : 0, "CarDir" :182.26, "SteelAng" : 0, "ErrContent" : ""},
		{"Index":62, "x" : 187.246, "y" : 16.387, "z" : 0, "Brake" : 0, "Clutch" : 0, "Accelerat" : 0, "CarDir" :182.26, "SteelAng" : 0, "ErrContent" : ""},
		{"Index":63, "x" : 187.246, "y" : 16.387, "z" : 0, "Brake" : 0, "Clutch" : 0, "Accelerat" : 0, "CarDir" :182.26, "SteelAng" : 0, "ErrContent" : ""},
		{"Index":64, "x" : 187.246, "y" : 16.387, "z" : 0, "Brake" : 0, "Clutch" : 0, "Accelerat" : 0, "CarDir" :182.26, "SteelAng" : 0, "ErrContent" : ""},
		{"Index":65, "x" : 187.246, "y" : 16.387, "z" : 0, "Brake" : 0, "Clutch" : 0, "Accelerat" : 0, "CarDir" :182.26, "SteelAng" : 0, "ErrContent" : ""},
		{"Index":66, "x" : 187.246, "y" : 16.387, "z" : 0, "Brake" : 0, "Clutch" : 0, "Accelerat" : 0, "CarDir" :182.26, "SteelAng" : 0, "ErrContent" : ""},
		{"Index":67, "x" : 187.246, "y" : 16.387, "z" : 0, "Brake" : 0, "Clutch" : 0, "Accelerat" : 0, "CarDir" :182.26, "SteelAng" : 0, "ErrContent" : ""},
		{"Index":68, "x" : 187.246, "y" : 16.387, "z" : 0, "Brake" : 0, "Clutch" : 0, "Accelerat" : 0, "CarDir" :182.26, "SteelAng" : 0, "ErrContent" : ""},
		{"Index":69, "x" : 187.246, "y" : 16.387, "z" : 0, "Brake" : 0, "Clutch" : 0, "Accelerat" : 0, "CarDir" :182.26, "SteelAng" : 0, "ErrContent" : ""},
		{"Index":70, "x" : 187.246, "y" : 16.387, "z" : 0, "Brake" : 0, "Clutch" : 0, "Accelerat" : 0, "CarDir" :182.26, "SteelAng" : 0, "ErrContent" : ""},
		{"Index":71, "x" : 187.246, "y" : 16.387, "z" : 0, "Brake" : 0, "Clutch" : 0, "Accelerat" : 0, "CarDir" :182.26, "SteelAng" : 0, "ErrContent" : ""},
		{"Index":72, "x" : 187.246, "y" : 16.387, "z" : 0, "Brake" : 0, "Clutch" : 0, "Accelerat" : 0, "CarDir" :182.26, "SteelAng" : 0, "ErrContent" : ""},
		{"Index":73, "x" : 187.246, "y" : 16.387, "z" : 0, "Brake" : 0, "Clutch" : 0, "Accelerat" : 0, "CarDir" :182.26, "SteelAng" : 0, "ErrContent" : ""},
		{"Index":74, "x" : 187.246, "y" : 16.387, "z" : 0, "Brake" : 0, "Clutch" : 0, "Accelerat" : 0, "CarDir" :182.26, "SteelAng" : 0, "ErrContent" : ""},
		{"Index":75, "x" : 187.246, "y" : 16.387, "z" : 0, "Brake" : 0, "Clutch" : 0, "Accelerat" : 0, "CarDir" :182.26, "SteelAng" : 0, "ErrContent" : ""},
		{"Index":76, "x" : 187.246, "y" : 16.387, "z" : 0, "Brake" : 0, "Clutch" : 0, "Accelerat" : 0, "CarDir" :182.26, "SteelAng" : 0, "ErrContent" : ""},
		{"Index":77, "x" : 187.246, "y" : 16.387, "z" : 0, "Brake" : 0, "Clutch" : 0, "Accelerat" : 0, "CarDir" :182.26, "SteelAng" : 0, "ErrContent" : ""},
		{"Index":78, "x" : 187.246, "y" : 16.387, "z" : 0, "Brake" : 0, "Clutch" : 0, "Accelerat" : 0, "CarDir" :182.26, "SteelAng" : 0, "ErrContent" : ""},
		{"Index":79, "x" : 187.245, "y" : 16.407, "z" : 0, "Brake" : 0, "Clutch" : 0, "Accelerat" : 0, "CarDir" :182.26, "SteelAng" : 0, "ErrContent" : ""},
		{"Index":80, "x" : 187.244, "y" : 16.427, "z" : 0, "Brake" : 0, "Clutch" : 0, "Accelerat" : 0, "CarDir" :182.26, "SteelAng" : 0, "ErrContent" : ""},
		{"Index":81, "x" : 187.244, "y" : 16.427, "z" : 0, "Brake" : 0, "Clutch" : 0, "Accelerat" : 0, "CarDir" :182.26, "SteelAng" : 0, "ErrContent" : ""},
		{"Index":82, "x" : 187.244, "y" : 16.447, "z" : 0, "Brake" : 0, "Clutch" : 0, "Accelerat" : 0, "CarDir" :182.26, "SteelAng" : 0, "ErrContent" : ""},
		{"Index":83, "x" : 187.243, "y" : 16.467, "z" : 0, "Brake" : 0, "Clutch" : 0, "Accelerat" : 0, "CarDir" :182.26, "SteelAng" : 0, "ErrContent" : ""},
		{"Index":84, "x" : 187.243, "y" : 16.467, "z" : 0, "Brake" : 0, "Clutch" : 0, "Accelerat" : 0, "CarDir" :182.26, "SteelAng" : 0, "ErrContent" : ""},
		{"Index":85, "x" : 187.243, "y" : 16.467, "z" : 0, "Brake" : 0, "Clutch" : 0, "Accelerat" : 0, "CarDir" :182.26, "SteelAng" : 0, "ErrContent" : ""},
		{"Index":86, "x" : 187.242, "y" : 16.507, "z" : 0, "Brake" : 0, "Clutch" : 0, "Accelerat" : 0, "CarDir" :182.26, "SteelAng" : 0, "ErrContent" : ""},
		{"Index":87, "x" : 187.241, "y" : 16.527, "z" : 0, "Brake" : 0, "Clutch" : 0, "Accelerat" : 0, "CarDir" :182.26, "SteelAng" : 0, "ErrContent" : ""},
		{"Index":88, "x" : 187.24, "y" : 16.547, "z" : 0, "Brake" : 0, "Clutch" : 0, "Accelerat" : 0, "CarDir" :182.26, "SteelAng" : 0, "ErrContent" : ""},
		{"Index":89, "x" : 187.24, "y" : 16.567, "z" : 0, "Brake" : 0, "Clutch" : 0, "Accelerat" : 0, "CarDir" :182.26, "SteelAng" : 0, "ErrContent" : ""},
		{"Index":90, "x" : 187.24, "y" : 16.567, "z" : 0, "Brake" : 0, "Clutch" : 0, "Accelerat" : 0, "CarDir" :182.26, "SteelAng" : 0, "ErrContent" : ""},
		{"Index":91, "x" : 187.239, "y" : 16.587, "z" : 0, "Brake" : 0, "Clutch" : 0, "Accelerat" : 0, "CarDir" :182.26, "SteelAng" : 0, "ErrContent" : ""},
		{"Index":92, "x" : 187.237, "y" : 16.647, "z" : 0, "Brake" : 0, "Clutch" : 0, "Accelerat" : 0, "CarDir" :182.26, "SteelAng" : 0, "ErrContent" : ""},
		{"Index":93, "x" : 187.236, "y" : 16.667, "z" : 0, "Brake" : 0, "Clutch" : 0, "Accelerat" : 0, "CarDir" :182.26, "SteelAng" : 0, "ErrContent" : ""},
		{"Index":94, "x" : 187.236, "y" : 16.667, "z" : 0, "Brake" : 0, "Clutch" : 0, "Accelerat" : 0, "CarDir" :182.26, "SteelAng" : 0, "ErrContent" : ""},
		{"Index":95, "x" : 187.236, "y" : 16.667, "z" : 0, "Brake" : 0, "Clutch" : 0, "Accelerat" : 0, "CarDir" :182.26, "SteelAng" : 0, "ErrContent" : ""},
		{"Index":96, "x" : 187.235, "y" : 16.707, "z" : 0, "Brake" : 0, "Clutch" : 0, "Accelerat" : 0, "CarDir" :182.26, "SteelAng" : 0, "ErrContent" : ""},
		{"Index":97, "x" : 187.234, "y" : 16.727, "z" : 0, "Brake" : 0, "Clutch" : 0, "Accelerat" : 0, "CarDir" :182.26, "SteelAng" : 0, "ErrContent" : ""},
		{"Index":98, "x" : 187.234, "y" : 16.727, "z" : 0, "Brake" : 0, "Clutch" : 0, "Accelerat" : 0, "CarDir" :182.26, "SteelAng" : 0, "ErrContent" : ""},
		{"Index":99, "x" : 187.234, "y" : 16.747, "z" : 0, "Brake" : 0, "Clutch" : 0, "Accelerat" : 0, "CarDir" :182.26, "SteelAng" : 0, "ErrContent" : ""},
		{"Index":100, "x" : 187.233, "y" : 16.767, "z" : 0, "Brake" : 0, "Clutch" : 0, "Accelerat" : 0, "CarDir" :182.26, "SteelAng" : 0, "ErrContent" : ""},
		{"Index":101, "x" : 187.233, "y" : 16.767, "z" : 0, "Brake" : 0, "Clutch" : 0, "Accelerat" : 0, "CarDir" :182.26, "SteelAng" : 0, "ErrContent" : ""},
		{"Index":102, "x" : 187.232, "y" : 16.807, "z" : 0, "Brake" : 0, "Clutch" : 0, "Accelerat" : 0, "CarDir" :182.26, "SteelAng" : 0, "ErrContent" : ""},
		{"Index":103, "x" : 187.231, "y" : 16.827, "z" : 0, "Brake" : 0, "Clutch" : 0, "Accelerat" : 0, "CarDir" :182.26, "SteelAng" : 0, "ErrContent" : ""},
		{"Index":104, "x" : 187.231, "y" : 16.827, "z" : 0, "Brake" : 0, "Clutch" : 0, "Accelerat" : 0, "CarDir" :182.26, "SteelAng" : 0, "ErrContent" : ""},
		{"Index":105, "x" : 187.231, "y" : 16.827, "z" : 0, "Brake" : 0, "Clutch" : 0, "Accelerat" : 0, "CarDir" :182.26, "SteelAng" : 0, "ErrContent" : ""},
		{"Index":106, "x" : 187.231, "y" : 16.827, "z" : 0, "Brake" : 0, "Clutch" : 0, "Accelerat" : 0, "CarDir" :182.26, "SteelAng" : 0, "ErrContent" : ""},
		{"Index":107, "x" : 187.231, "y" : 16.827, "z" : 0, "Brake" : 0, "Clutch" : 0, "Accelerat" : 0, "CarDir" :182.26, "SteelAng" : 0, "ErrContent" : ""},
		{"Index":108, "x" : 187.231, "y" : 16.827, "z" : 0, "Brake" : 0, "Clutch" : 0, "Accelerat" : 0, "CarDir" :182.26, "SteelAng" : 0, "ErrContent" : ""},
		{"Index":109, "x" : 187.228, "y" : 16.907, "z" : 0, "Brake" : 0, "Clutch" : 0, "Accelerat" : 0, "CarDir" :182.26, "SteelAng" : 0, "ErrContent" : ""},
		{"Index":110, "x" : 187.228, "y" : 16.907, "z" : 0, "Brake" : 0, "Clutch" : 0, "Accelerat" : 0, "CarDir" :182.26, "SteelAng" : 0, "ErrContent" : ""},
		{"Index":111, "x" : 187.228, "y" : 16.907, "z" : 0, "Brake" : 0, "Clutch" : 0, "Accelerat" : 0, "CarDir" :182.26, "SteelAng" : 0, "ErrContent" : ""},
		{"Index":112, "x" : 187.228, "y" : 16.927, "z" : 0, "Brake" : 0, "Clutch" : 0, "Accelerat" : 0, "CarDir" :182.26, "SteelAng" : 0, "ErrContent" : ""},
		{"Index":113, "x" : 187.227, "y" : 16.947, "z" : 0, "Brake" : 0, "Clutch" : 0, "Accelerat" : 0, "CarDir" :182.26, "SteelAng" : 0, "ErrContent" : ""},
		{"Index":114, "x" : 187.227, "y" : 16.947, "z" : 0, "Brake" : 0, "Clutch" : 0, "Accelerat" : 0, "CarDir" :182.26, "SteelAng" : 0, "ErrContent" : ""},
		{"Index":115, "x" : 187.227, "y" : 16.947, "z" : 0, "Brake" : 0, "Clutch" : 0, "Accelerat" : 0, "CarDir" :182.26, "SteelAng" : 0, "ErrContent" : ""},
		{"Index":116, "x" : 187.226, "y" : 16.987, "z" : 0, "Brake" : 0, "Clutch" : 0, "Accelerat" : 0, "CarDir" :182.26, "SteelAng" : 0, "ErrContent" : ""},
		{"Index":117, "x" : 187.225, "y" : 17.007, "z" : 0, "Brake" : 0, "Clutch" : 0, "Accelerat" : 0, "CarDir" :182.26, "SteelAng" : 0, "ErrContent" : ""},
		{"Index":118, "x" : 187.224, "y" : 17.027, "z" : 0, "Brake" : 0, "Clutch" : 0, "Accelerat" : 0, "CarDir" :182.26, "SteelAng" : 0, "ErrContent" : ""},
		{"Index":119, "x" : 187.224, "y" : 17.027, "z" : 0, "Brake" : 0, "Clutch" : 0, "Accelerat" : 0, "CarDir" :182.26, "SteelAng" : 0, "ErrContent" : ""},
		{"Index":120, "x" : 187.224, "y" : 17.047, "z" : 0, "Brake" : 0, "Clutch" : 0, "Accelerat" : 0, "CarDir" :182.26, "SteelAng" : 0, "ErrContent" : ""},
		{"Index":121, "x" : 187.223, "y" : 17.067, "z" : 0, "Brake" : 0, "Clutch" : 0, "Accelerat" : 0, "CarDir" :182.26, "SteelAng" : 0, "ErrContent" : ""},
		{"Index":122, "x" : 187.222, "y" : 17.087, "z" : 0, "Brake" : 0, "Clutch" : 0, "Accelerat" : 0, "CarDir" :182.26, "SteelAng" : 0, "ErrContent" : ""},
		{"Index":123, "x" : 187.222, "y" : 17.107, "z" : 0, "Brake" : 0, "Clutch" : 0, "Accelerat" : 0, "CarDir" :182.26, "SteelAng" : 0, "ErrContent" : ""},
		{"Index":124, "x" : 187.222, "y" : 17.107, "z" : 0, "Brake" : 0, "Clutch" : 0, "Accelerat" : 0, "CarDir" :182.26, "SteelAng" : 0, "ErrContent" : ""},
		{"Index":125, "x" : 187.221, "y" : 17.127, "z" : 0, "Brake" : 0, "Clutch" : 0, "Accelerat" : 0, "CarDir" :182.26, "SteelAng" : 0, "ErrContent" : ""},
		{"Index":126, "x" : 187.22, "y" : 17.147, "z" : 0, "Brake" : 0, "Clutch" : 0, "Accelerat" : 0, "CarDir" :182.26, "SteelAng" : 0, "ErrContent" : ""},
		{"Index":127, "x" : 187.22, "y" : 17.167, "z" : 0, "Brake" : 0, "Clutch" : 0, "Accelerat" : 0, "CarDir" :182.26, "SteelAng" : 0, "ErrContent" : ""},
		{"Index":128, "x" : 187.22, "y" : 17.167, "z" : 0, "Brake" : 0, "Clutch" : 0, "Accelerat" : 0, "CarDir" :182.26, "SteelAng" : 0, "ErrContent" : ""},
		{"Index":129, "x" : 187.219, "y" : 17.187, "z" : 0, "Brake" : 0, "Clutch" : 0, "Accelerat" : 0, "CarDir" :182.26, "SteelAng" : 0, "ErrContent" : ""},
		{"Index":130, "x" : 187.219, "y" : 17.187, "z" : 0, "Brake" : 0, "Clutch" : 0, "Accelerat" : 0, "CarDir" :182.26, "SteelAng" : 0, "ErrContent" : ""},
		{"Index":131, "x" : 187.218, "y" : 17.227, "z" : 0, "Brake" : 0, "Clutch" : 0, "Accelerat" : 0, "CarDir" :182.26, "SteelAng" : 0, "ErrContent" : ""},
		{"Index":132, "x" : 187.217, "y" : 17.247, "z" : 0, "Brake" : 0, "Clutch" : 0, "Accelerat" : 0, "CarDir" :182.26, "SteelAng" : 0, "ErrContent" : ""},
		{"Index":133, "x" : 187.217, "y" : 17.247, "z" : 0, "Brake" : 0, "Clutch" : 0, "Accelerat" : 0, "CarDir" :182.26, "SteelAng" : 0, "ErrContent" : ""},
		{"Index":134, "x" : 187.216, "y" : 17.267, "z" : 0, "Brake" : 0, "Clutch" : 0, "Accelerat" : 0, "CarDir" :182.26, "SteelAng" : 0, "ErrContent" : ""},
		{"Index":135, "x" : 187.216, "y" : 17.267, "z" : 0, "Brake" : 0, "Clutch" : 0, "Accelerat" : 0, "CarDir" :182.26, "SteelAng" : 0, "ErrContent" : ""},
		{"Index":136, "x" : 187.215, "y" : 17.307, "z" : 0, "Brake" : 0, "Clutch" : 0, "Accelerat" : 0, "CarDir" :182.26, "SteelAng" : 0, "ErrContent" : ""},
		{"Index":137, "x" : 187.215, "y" : 17.307, "z" : 0, "Brake" : 0, "Clutch" : 0, "Accelerat" : 0, "CarDir" :182.26, "SteelAng" : 0, "ErrContent" : ""},
		{"Index":138, "x" : 187.214, "y" : 17.327, "z" : 0, "Brake" : 0, "Clutch" : 0, "Accelerat" : 0, "CarDir" :182.26, "SteelAng" : 0, "ErrContent" : ""},
		{"Index":139, "x" : 187.213, "y" : 17.347, "z" : 0, "Brake" : 0, "Clutch" : 0, "Accelerat" : 0, "CarDir" :182.26, "SteelAng" : 0, "ErrContent" : ""},
		{"Index":140, "x" : 187.213, "y" : 17.367, "z" : 0, "Brake" : 0, "Clutch" : 0, "Accelerat" : 0, "CarDir" :182.26, "SteelAng" : 0, "ErrContent" : ""},
		{"Index":141, "x" : 187.212, "y" : 17.387, "z" : 0, "Brake" : 0, "Clutch" : 0, "Accelerat" : 0, "CarDir" :182.26, "SteelAng" : 0, "ErrContent" : ""},
		{"Index":142, "x" : 187.212, "y" : 17.387, "z" : 0, "Brake" : 0, "Clutch" : 0, "Accelerat" : 0, "CarDir" :182.26, "SteelAng" : 0, "ErrContent" : ""},
		{"Index":143, "x" : 187.211, "y" : 17.407, "z" : 0, "Brake" : 0, "Clutch" : 0, "Accelerat" : 0, "CarDir" :182.26, "SteelAng" : 0, "ErrContent" : ""},
		{"Index":144, "x" : 187.211, "y" : 17.427, "z" : 0, "Brake" : 0, "Clutch" : 0, "Accelerat" : 0, "CarDir" :182.26, "SteelAng" : 0, "ErrContent" : ""},
		{"Index":145, "x" : 187.211, "y" : 17.427, "z" : 0, "Brake" : 0, "Clutch" : 0, "Accelerat" : 0, "CarDir" :182.26, "SteelAng" : 0, "ErrContent" : ""},
		{"Index":146, "x" : 187.21, "y" : 17.447, "z" : 0, "Brake" : 0, "Clutch" : 0, "Accelerat" : 0, "CarDir" :182.26, "SteelAng" : 0, "ErrContent" : ""},
		{"Index":147, "x" : 187.21, "y" : 17.447, "z" : 0, "Brake" : 0, "Clutch" : 0, "Accelerat" : 0, "CarDir" :182.26, "SteelAng" : 0, "ErrContent" : ""},
		{"Index":148, "x" : 187.21, "y" : 17.447, "z" : 0, "Brake" : 0, "Clutch" : 0, "Accelerat" : 0, "CarDir" :182.26, "SteelAng" : 0, "ErrContent" : ""},
		{"Index":149, "x" : 187.209, "y" : 17.487, "z" : 0, "Brake" : 0, "Clutch" : 0, "Accelerat" : 0, "CarDir" :182.26, "SteelAng" : 0, "ErrContent" : ""},
		{"Index":150, "x" : 187.209, "y" : 17.487, "z" : 0, "Brake" : 0, "Clutch" : 0, "Accelerat" : 0, "CarDir" :182.26, "SteelAng" : 0, "ErrContent" : ""},
		{"Index":151, "x" : 187.207, "y" : 17.527, "z" : 0, "Brake" : 0, "Clutch" : 0, "Accelerat" : 0, "CarDir" :182.26, "SteelAng" : 0, "ErrContent" : ""},
		{"Index":152, "x" : 187.207, "y" : 17.547, "z" : 0, "Brake" : 0, "Clutch" : 0, "Accelerat" : 0, "CarDir" :182.26, "SteelAng" : 0, "ErrContent" : ""},
		{"Index":153, "x" : 187.207, "y" : 17.547, "z" : 0, "Brake" : 0, "Clutch" : 0, "Accelerat" : 0, "CarDir" :182.26, "SteelAng" : 0, "ErrContent" : ""},
		{"Index":154, "x" : 187.206, "y" : 17.567, "z" : 0, "Brake" : 0, "Clutch" : 0, "Accelerat" : 0, "CarDir" :182.26, "SteelAng" : 0, "ErrContent" : ""},
		{"Index":155, "x" : 187.205, "y" : 17.587, "z" : 0, "Brake" : 0, "Clutch" : 0, "Accelerat" : 0, "CarDir" :182.26, "SteelAng" : 0, "ErrContent" : ""},
		{"Index":156, "x" : 187.205, "y" : 17.606, "z" : 0, "Brake" : 0, "Clutch" : 0, "Accelerat" : 0, "CarDir" :182.26, "SteelAng" : 0, "ErrContent" : ""},
		{"Index":157, "x" : 187.205, "y" : 17.606, "z" : 0, "Brake" : 0, "Clutch" : 0, "Accelerat" : 0, "CarDir" :182.26, "SteelAng" : 0, "ErrContent" : ""},
		{"Index":158, "x" : 187.204, "y" : 17.626, "z" : 0, "Brake" : 0, "Clutch" : 0, "Accelerat" : 0, "CarDir" :182.26, "SteelAng" : 0, "ErrContent" : ""},
		{"Index":159, "x" : 187.203, "y" : 17.646, "z" : 0, "Brake" : 0, "Clutch" : 0, "Accelerat" : 0, "CarDir" :182.26, "SteelAng" : 0, "ErrContent" : ""},
		{"Index":160, "x" : 186.911, "y" : 19.26, "z" : 0, "Brake" : 0, "Clutch" : 0, "Accelerat" : 0, "CarDir" :163.15, "SteelAng" : -540, "ErrContent" : ""},
		{"Index":161, "x" : 186.907, "y" : 19.299, "z" : 0, "Brake" : 0, "Clutch" : 0, "Accelerat" : 0, "CarDir" :162.43, "SteelAng" : -540, "ErrContent" : ""},
		{"Index":162, "x" : 186.907, "y" : 19.299, "z" : 0, "Brake" : 0, "Clutch" : 0, "Accelerat" : 0, "CarDir" :162.43, "SteelAng" : -540, "ErrContent" : ""},
		{"Index":163, "x" : 186.907, "y" : 19.299, "z" : 0, "Brake" : 0, "Clutch" : 0, "Accelerat" : 0, "CarDir" :162.43, "SteelAng" : -540, "ErrContent" : ""},
		{"Index":164, "x" : 186.901, "y" : 19.357, "z" : 0, "Brake" : 0, "Clutch" : 0, "Accelerat" : 0, "CarDir" :161.35, "SteelAng" : -540, "ErrContent" : ""},
		{"Index":165, "x" : 186.901, "y" : 19.357, "z" : 0, "Brake" : 0, "Clutch" : 0, "Accelerat" : 0, "CarDir" :161.35, "SteelAng" : -540, "ErrContent" : ""},
		{"Index":166, "x" : 186.899, "y" : 19.376, "z" : 0, "Brake" : 0, "Clutch" : 0, "Accelerat" : 0, "CarDir" :160.99, "SteelAng" : -540, "ErrContent" : ""},
		{"Index":167, "x" : 186.899, "y" : 19.376, "z" : 0, "Brake" : 0, "Clutch" : 0, "Accelerat" : 0, "CarDir" :160.99, "SteelAng" : -540, "ErrContent" : ""},
		{"Index":168, "x" : 186.899, "y" : 19.376, "z" : 0, "Brake" : 0, "Clutch" : 0, "Accelerat" : 0, "CarDir" :160.99, "SteelAng" : -540, "ErrContent" : ""},
		{"Index":169, "x" : 186.899, "y" : 19.376, "z" : 0, "Brake" : 0, "Clutch" : 0, "Accelerat" : 0, "CarDir" :160.99, "SteelAng" : -540, "ErrContent" : ""},
		{"Index":170, "x" : 186.894, "y" : 19.453, "z" : 0, "Brake" : 0, "Clutch" : 0, "Accelerat" : 0, "CarDir" :159.55, "SteelAng" : -540, "ErrContent" : ""},
		{"Index":171, "x" : 186.894, "y" : 19.453, "z" : 0, "Brake" : 0, "Clutch" : 0, "Accelerat" : 0, "CarDir" :159.55, "SteelAng" : -540, "ErrContent" : ""},
		{"Index":172, "x" : 186.894, "y" : 19.453, "z" : 0, "Brake" : 0, "Clutch" : 0, "Accelerat" : 0, "CarDir" :159.55, "SteelAng" : -540, "ErrContent" : ""},
		{"Index":173, "x" : 186.891, "y" : 19.512, "z" : 0, "Brake" : 0, "Clutch" : 0, "Accelerat" : 0, "CarDir" :158.47, "SteelAng" : -540, "ErrContent" : ""},
		{"Index":174, "x" : 186.89, "y" : 19.531, "z" : 0, "Brake" : 0, "Clutch" : 0, "Accelerat" : 0, "CarDir" :158.11, "SteelAng" : -540, "ErrContent" : ""},
		{"Index":175, "x" : 186.89, "y" : 19.531, "z" : 0, "Brake" : 0, "Clutch" : 0, "Accelerat" : 0, "CarDir" :158.11, "SteelAng" : -540, "ErrContent" : ""},
		{"Index":176, "x" : 186.89, "y" : 19.531, "z" : 0, "Brake" : 0, "Clutch" : 0, "Accelerat" : 0, "CarDir" :158.11, "SteelAng" : -540, "ErrContent" : ""},
		{"Index":177, "x" : 186.89, "y" : 19.531, "z" : 0, "Brake" : 0, "Clutch" : 0, "Accelerat" : 0, "CarDir" :158.11, "SteelAng" : -540, "ErrContent" : ""},
		{"Index":178, "x" : 186.888, "y" : 19.59, "z" : 0, "Brake" : 0, "Clutch" : 0, "Accelerat" : 0, "CarDir" :157.03, "SteelAng" : -540, "ErrContent" : ""},
		{"Index":179, "x" : 186.888, "y" : 19.609, "z" : 0, "Brake" : 0, "Clutch" : 0, "Accelerat" : 0, "CarDir" :156.67, "SteelAng" : -540, "ErrContent" : ""},
		{"Index":180, "x" : 186.888, "y" : 19.629, "z" : 0, "Brake" : 0, "Clutch" : 0, "Accelerat" : 0, "CarDir" :156.31, "SteelAng" : -540, "ErrContent" : ""},
		{"Index":181, "x" : 186.888, "y" : 19.648, "z" : 0, "Brake" : 0, "Clutch" : 0, "Accelerat" : 0, "CarDir" :155.95, "SteelAng" : -540, "ErrContent" : ""},
		{"Index":182, "x" : 186.888, "y" : 19.668, "z" : 0, "Brake" : 0, "Clutch" : 0, "Accelerat" : 0, "CarDir" :155.59, "SteelAng" : -540, "ErrContent" : ""},
		{"Index":183, "x" : 186.888, "y" : 19.668, "z" : 0, "Brake" : 0, "Clutch" : 0, "Accelerat" : 0, "CarDir" :155.59, "SteelAng" : -540, "ErrContent" : ""},
		{"Index":184, "x" : 186.888, "y" : 19.668, "z" : 0, "Brake" : 0, "Clutch" : 0, "Accelerat" : 0, "CarDir" :155.59, "SteelAng" : -540, "ErrContent" : ""},
		{"Index":185, "x" : 186.889, "y" : 19.727, "z" : 0, "Brake" : 0, "Clutch" : 0, "Accelerat" : 0, "CarDir" :154.51, "SteelAng" : -540, "ErrContent" : ""},
		{"Index":186, "x" : 186.889, "y" : 19.747, "z" : 0, "Brake" : 0, "Clutch" : 0, "Accelerat" : 0, "CarDir" :154.15, "SteelAng" : -540, "ErrContent" : ""},
		{"Index":187, "x" : 186.89, "y" : 19.766, "z" : 0, "Brake" : 0, "Clutch" : 0, "Accelerat" : 0, "CarDir" :153.79, "SteelAng" : -540, "ErrContent" : ""},
		{"Index":188, "x" : 186.89, "y" : 19.766, "z" : 0, "Brake" : 0, "Clutch" : 0, "Accelerat" : 0, "CarDir" :153.79, "SteelAng" : -540, "ErrContent" : ""},
		{"Index":189, "x" : 186.89, "y" : 19.766, "z" : 0, "Brake" : 0, "Clutch" : 0, "Accelerat" : 0, "CarDir" :153.79, "SteelAng" : -540, "ErrContent" : ""},
		{"Index":190, "x" : 186.891, "y" : 19.806, "z" : 0, "Brake" : 0, "Clutch" : 0, "Accelerat" : 0, "CarDir" :153.07, "SteelAng" : -540, "ErrContent" : ""},
		{"Index":191, "x" : 186.892, "y" : 19.825, "z" : 0, "Brake" : 0, "Clutch" : 0, "Accelerat" : 0, "CarDir" :152.71, "SteelAng" : -540, "ErrContent" : ""},
		{"Index":192, "x" : 186.895, "y" : 19.865, "z" : 0, "Brake" : 0, "Clutch" : 0, "Accelerat" : 0, "CarDir" :151.99, "SteelAng" : -540, "ErrContent" : ""},
		{"Index":193, "x" : 186.895, "y" : 19.865, "z" : 0, "Brake" : 0, "Clutch" : 0, "Accelerat" : 0, "CarDir" :151.99, "SteelAng" : -540, "ErrContent" : ""},
		{"Index":194, "x" : 186.898, "y" : 19.904, "z" : 0, "Brake" : 0, "Clutch" : 0, "Accelerat" : 0, "CarDir" :151.27, "SteelAng" : -540, "ErrContent" : ""},
		{"Index":195, "x" : 186.899, "y" : 19.924, "z" : 0, "Brake" : 0, "Clutch" : 0, "Accelerat" : 0, "CarDir" :150.91, "SteelAng" : -540, "ErrContent" : ""},
		{"Index":196, "x" : 186.899, "y" : 19.924, "z" : 0, "Brake" : 0, "Clutch" : 0, "Accelerat" : 0, "CarDir" :150.91, "SteelAng" : -540, "ErrContent" : ""},
		{"Index":197, "x" : 186.901, "y" : 19.944, "z" : 0, "Brake" : 0, "Clutch" : 0, "Accelerat" : 0, "CarDir" :150.55, "SteelAng" : -540, "ErrContent" : ""},
		{"Index":198, "x" : 186.903, "y" : 19.963, "z" : 0, "Brake" : 0, "Clutch" : 0, "Accelerat" : 0, "CarDir" :150.18, "SteelAng" : -540, "ErrContent" : ""},
		{"Index":199, "x" : 186.903, "y" : 19.963, "z" : 0, "Brake" : 0, "Clutch" : 0, "Accelerat" : 0, "CarDir" :150.18, "SteelAng" : -540, "ErrContent" : ""},
		{"Index":200, "x" : 186.903, "y" : 19.963, "z" : 0, "Brake" : 0, "Clutch" : 0, "Accelerat" : 0, "CarDir" :150.18, "SteelAng" : -540, "ErrContent" : ""},
		{"Index":201, "x" : 186.903, "y" : 19.963, "z" : 0, "Brake" : 0, "Clutch" : 0, "Accelerat" : 0, "CarDir" :150.18, "SteelAng" : -540, "ErrContent" : ""},
		{"Index":202, "x" : 186.911, "y" : 20.042, "z" : 0, "Brake" : 0, "Clutch" : 0, "Accelerat" : 0, "CarDir" :148.74, "SteelAng" : -540, "ErrContent" : ""},
		{"Index":203, "x" : 186.911, "y" : 20.042, "z" : 0, "Brake" : 0, "Clutch" : 0, "Accelerat" : 0, "CarDir" :148.74, "SteelAng" : -540, "ErrContent" : ""},
		{"Index":204, "x" : 186.916, "y" : 20.082, "z" : 0, "Brake" : 0, "Clutch" : 0, "Accelerat" : 0, "CarDir" :148.02, "SteelAng" : -540, "ErrContent" : ""},
		{"Index":205, "x" : 186.919, "y" : 20.102, "z" : 0, "Brake" : 0, "Clutch" : 0, "Accelerat" : 0, "CarDir" :147.66, "SteelAng" : -540, "ErrContent" : ""},
		{"Index":206, "x" : 186.919, "y" : 20.102, "z" : 0, "Brake" : 0, "Clutch" : 0, "Accelerat" : 0, "CarDir" :147.66, "SteelAng" : -540, "ErrContent" : ""},
		{"Index":207, "x" : 186.919, "y" : 20.102, "z" : 0, "Brake" : 0, "Clutch" : 0, "Accelerat" : 0, "CarDir" :147.66, "SteelAng" : -540, "ErrContent" : ""},
		{"Index":208, "x" : 186.919, "y" : 20.102, "z" : 0, "Brake" : 0, "Clutch" : 0, "Accelerat" : 0, "CarDir" :147.66, "SteelAng" : -540, "ErrContent" : ""},
		{"Index":209, "x" : 186.919, "y" : 20.102, "z" : 0, "Brake" : 0, "Clutch" : 0, "Accelerat" : 0, "CarDir" :147.66, "SteelAng" : -540, "ErrContent" : ""},
		{"Index":210, "x" : 186.919, "y" : 20.102, "z" : 0, "Brake" : 0, "Clutch" : 0, "Accelerat" : 0, "CarDir" :147.66, "SteelAng" : -540, "ErrContent" : ""},
		{"Index":211, "x" : 186.919, "y" : 20.102, "z" : 0, "Brake" : 0, "Clutch" : 0, "Accelerat" : 0, "CarDir" :147.66, "SteelAng" : -540, "ErrContent" : ""},
		{"Index":212, "x" : 186.94, "y" : 20.24, "z" : 0, "Brake" : 0, "Clutch" : 0, "Accelerat" : 0, "CarDir" :145.14, "SteelAng" : -540, "ErrContent" : ""},
		{"Index":213, "x" : 186.94, "y" : 20.24, "z" : 0, "Brake" : 0, "Clutch" : 0, "Accelerat" : 0, "CarDir" :145.14, "SteelAng" : -540, "ErrContent" : ""},
		{"Index":214, "x" : 186.948, "y" : 20.279, "z" : 0, "Brake" : 0, "Clutch" : 0, "Accelerat" : 0, "CarDir" :144.42, "SteelAng" : -540, "ErrContent" : ""},
		{"Index":215, "x" : 186.951, "y" : 20.299, "z" : 0, "Brake" : 0, "Clutch" : 0, "Accelerat" : 0, "CarDir" :144.06, "SteelAng" : -540, "ErrContent" : ""},
		{"Index":216, "x" : 186.951, "y" : 20.299, "z" : 0, "Brake" : 0, "Clutch" : 0, "Accelerat" : 0, "CarDir" :144.06, "SteelAng" : -540, "ErrContent" : ""},
		{"Index":217, "x" : 186.955, "y" : 20.319, "z" : 0, "Brake" : 0, "Clutch" : 0, "Accelerat" : 0, "CarDir" :143.7, "SteelAng" : -540, "ErrContent" : ""},
		{"Index":218, "x" : 186.959, "y" : 20.338, "z" : 0, "Brake" : 0, "Clutch" : 0, "Accelerat" : 0, "CarDir" :143.34, "SteelAng" : -540, "ErrContent" : ""},
		{"Index":219, "x" : 186.963, "y" : 20.358, "z" : 0, "Brake" : 0, "Clutch" : 0, "Accelerat" : 0, "CarDir" :142.98, "SteelAng" : -540, "ErrContent" : ""},
		{"Index":220, "x" : 186.968, "y" : 20.378, "z" : 0, "Brake" : 0, "Clutch" : 0, "Accelerat" : 0, "CarDir" :142.62, "SteelAng" : -540, "ErrContent" : ""},
		{"Index":221, "x" : 186.972, "y" : 20.397, "z" : 0, "Brake" : 0, "Clutch" : 0, "Accelerat" : 0, "CarDir" :142.26, "SteelAng" : -540, "ErrContent" : ""},
		{"Index":222, "x" : 186.977, "y" : 20.417, "z" : 0, "Brake" : 0, "Clutch" : 0, "Accelerat" : 0, "CarDir" :141.9, "SteelAng" : -540, "ErrContent" : ""},
		{"Index":223, "x" : 186.981, "y" : 20.437, "z" : 0, "Brake" : 0, "Clutch" : 0, "Accelerat" : 0, "CarDir" :141.54, "SteelAng" : -540, "ErrContent" : ""},
		{"Index":224, "x" : 186.986, "y" : 20.456, "z" : 0, "Brake" : 0, "Clutch" : 0, "Accelerat" : 0, "CarDir" :141.18, "SteelAng" : -540, "ErrContent" : ""},
		{"Index":225, "x" : 186.991, "y" : 20.476, "z" : 0, "Brake" : 0, "Clutch" : 0, "Accelerat" : 0, "CarDir" :140.82, "SteelAng" : -540, "ErrContent" : ""},
		{"Index":226, "x" : 186.996, "y" : 20.495, "z" : 0, "Brake" : 0, "Clutch" : 0, "Accelerat" : 0, "CarDir" :140.46, "SteelAng" : -540, "ErrContent" : ""},
		{"Index":227, "x" : 187.001, "y" : 20.515, "z" : 0, "Brake" : 0, "Clutch" : 0, "Accelerat" : 0, "CarDir" :140.1, "SteelAng" : -540, "ErrContent" : ""},
		{"Index":228, "x" : 187.001, "y" : 20.515, "z" : 0, "Brake" : 0, "Clutch" : 0, "Accelerat" : 0, "CarDir" :140.1, "SteelAng" : -540, "ErrContent" : ""},
		{"Index":229, "x" : 187.006, "y" : 20.535, "z" : 0, "Brake" : 0, "Clutch" : 0, "Accelerat" : 0, "CarDir" :139.74, "SteelAng" : -540, "ErrContent" : ""},
		{"Index":230, "x" : 187.011, "y" : 20.554, "z" : 0, "Brake" : 0, "Clutch" : 0, "Accelerat" : 0, "CarDir" :139.38, "SteelAng" : -540, "ErrContent" : ""},
		{"Index":231, "x" : 187.017, "y" : 20.574, "z" : 0, "Brake" : 0, "Clutch" : 0, "Accelerat" : 0, "CarDir" :139.02, "SteelAng" : -540, "ErrContent" : ""},
		{"Index":232, "x" : 187.017, "y" : 20.574, "z" : 0, "Brake" : 0, "Clutch" : 0, "Accelerat" : 0, "CarDir" :139.02, "SteelAng" : -540, "ErrContent" : ""},
		{"Index":233, "x" : 187.017, "y" : 20.574, "z" : 0, "Brake" : 0, "Clutch" : 0, "Accelerat" : 0, "CarDir" :139.02, "SteelAng" : -540, "ErrContent" : ""},
		{"Index":234, "x" : 187.033, "y" : 20.632, "z" : 0, "Brake" : 0, "Clutch" : 0, "Accelerat" : 0, "CarDir" :137.94, "SteelAng" : -540, "ErrContent" : ""},
		{"Index":235, "x" : 187.033, "y" : 20.632, "z" : 0, "Brake" : 0, "Clutch" : 0, "Accelerat" : 0, "CarDir" :137.94, "SteelAng" : -540, "ErrContent" : ""},
		{"Index":236, "x" : 187.033, "y" : 20.632, "z" : 0, "Brake" : 0, "Clutch" : 0, "Accelerat" : 0, "CarDir" :137.94, "SteelAng" : -540, "ErrContent" : ""},
		{"Index":237, "x" : 187.033, "y" : 20.632, "z" : 0, "Brake" : 0, "Clutch" : 0, "Accelerat" : 0, "CarDir" :137.94, "SteelAng" : -540, "ErrContent" : ""},
		{"Index":238, "x" : 187.033, "y" : 20.632, "z" : 0, "Brake" : 0, "Clutch" : 0, "Accelerat" : 0, "CarDir" :137.94, "SteelAng" : -540, "ErrContent" : ""},
		{"Index":239, "x" : 187.058, "y" : 20.709, "z" : 0, "Brake" : 0, "Clutch" : 0, "Accelerat" : 0, "CarDir" :136.5, "SteelAng" : -540, "ErrContent" : ""},
		{"Index":240, "x" : 187.064, "y" : 20.729, "z" : 0, "Brake" : 0, "Clutch" : 0, "Accelerat" : 0, "CarDir" :136.14, "SteelAng" : -540, "ErrContent" : ""},
		{"Index":241, "x" : 187.064, "y" : 20.729, "z" : 0, "Brake" : 0, "Clutch" : 0, "Accelerat" : 0, "CarDir" :136.14, "SteelAng" : -540, "ErrContent" : ""},
		{"Index":242, "x" : 187.064, "y" : 20.729, "z" : 0, "Brake" : 0, "Clutch" : 0, "Accelerat" : 0, "CarDir" :136.14, "SteelAng" : -540, "ErrContent" : ""},
		{"Index":243, "x" : 187.064, "y" : 20.729, "z" : 0, "Brake" : 0, "Clutch" : 0, "Accelerat" : 0, "CarDir" :136.14, "SteelAng" : -540, "ErrContent" : ""},
		{"Index":244, "x" : 187.083, "y" : 20.786, "z" : 0, "Brake" : 0, "Clutch" : 0, "Accelerat" : 0, "CarDir" :135.05, "SteelAng" : -540, "ErrContent" : ""},
		{"Index":245, "x" : 187.083, "y" : 20.786, "z" : 0, "Brake" : 0, "Clutch" : 0, "Accelerat" : 0, "CarDir" :135.05, "SteelAng" : -540, "ErrContent" : ""},
		{"Index":246, "x" : 187.097, "y" : 20.825, "z" : 0, "Brake" : 0, "Clutch" : 0, "Accelerat" : 0, "CarDir" :134.33, "SteelAng" : -540, "ErrContent" : ""},
		{"Index":247, "x" : 187.097, "y" : 20.825, "z" : 0, "Brake" : 0, "Clutch" : 0, "Accelerat" : 0, "CarDir" :134.33, "SteelAng" : -540, "ErrContent" : ""},
		{"Index":248, "x" : 187.097, "y" : 20.825, "z" : 0, "Brake" : 0, "Clutch" : 0, "Accelerat" : 0, "CarDir" :134.33, "SteelAng" : -540, "ErrContent" : ""},
		{"Index":249, "x" : 187.111, "y" : 20.863, "z" : 0, "Brake" : 0, "Clutch" : 0, "Accelerat" : 0, "CarDir" :133.61, "SteelAng" : -540, "ErrContent" : ""},
		{"Index":250, "x" : 187.111, "y" : 20.863, "z" : 0, "Brake" : 0, "Clutch" : 0, "Accelerat" : 0, "CarDir" :133.61, "SteelAng" : -540, "ErrContent" : ""},
		{"Index":251, "x" : 187.111, "y" : 20.863, "z" : 0, "Brake" : 0, "Clutch" : 0, "Accelerat" : 0, "CarDir" :133.61, "SteelAng" : -540, "ErrContent" : ""},
		{"Index":252, "x" : 187.111, "y" : 20.863, "z" : 0, "Brake" : 0, "Clutch" : 0, "Accelerat" : 0, "CarDir" :133.61, "SteelAng" : -540, "ErrContent" : ""},
		{"Index":253, "x" : 187.111, "y" : 20.863, "z" : 0, "Brake" : 0, "Clutch" : 0, "Accelerat" : 0, "CarDir" :133.61, "SteelAng" : -540, "ErrContent" : ""},
		{"Index":254, "x" : 187.14, "y" : 20.939, "z" : 0, "Brake" : 0, "Clutch" : 0, "Accelerat" : 0, "CarDir" :132.17, "SteelAng" : -540, "ErrContent" : ""},
		{"Index":255, "x" : 187.148, "y" : 20.957, "z" : 0, "Brake" : 0, "Clutch" : 0, "Accelerat" : 0, "CarDir" :131.81, "SteelAng" : -540, "ErrContent" : ""},
		{"Index":256, "x" : 187.148, "y" : 20.957, "z" : 0, "Brake" : 0, "Clutch" : 0, "Accelerat" : 0, "CarDir" :131.45, "SteelAng" : -540, "ErrContent" : ""},
		{"Index":257, "x" : 187.156, "y" : 20.976, "z" : 0, "Brake" : 0, "Clutch" : 0, "Accelerat" : 0, "CarDir" :131.45, "SteelAng" : -540, "ErrContent" : ""},
		{"Index":258, "x" : 187.163, "y" : 20.995, "z" : 0, "Brake" : 0, "Clutch" : 0, "Accelerat" : 0, "CarDir" :131.09, "SteelAng" : -540, "ErrContent" : ""},
		{"Index":259, "x" : 187.163, "y" : 20.995, "z" : 0, "Brake" : 0, "Clutch" : 0, "Accelerat" : 0, "CarDir" :131.09, "SteelAng" : -540, "ErrContent" : ""},
		{"Index":260, "x" : 187.179, "y" : 21.033, "z" : 0, "Brake" : 0, "Clutch" : 0, "Accelerat" : 0, "CarDir" :130.37, "SteelAng" : -540, "ErrContent" : ""},
		{"Index":261, "x" : 187.179, "y" : 21.033, "z" : 0, "Brake" : 0, "Clutch" : 0, "Accelerat" : 0, "CarDir" :130.37, "SteelAng" : -540, "ErrContent" : ""},
		{"Index":262, "x" : 187.179, "y" : 21.033, "z" : 0, "Brake" : 0, "Clutch" : 0, "Accelerat" : 0, "CarDir" :130.37, "SteelAng" : -540, "ErrContent" : ""},
		{"Index":263, "x" : 187.179, "y" : 21.033, "z" : 0, "Brake" : 0, "Clutch" : 0, "Accelerat" : 0, "CarDir" :130.37, "SteelAng" : -540, "ErrContent" : ""},
		{"Index":264, "x" : 187.204, "y" : 21.088, "z" : 0, "Brake" : 0, "Clutch" : 0, "Accelerat" : 0, "CarDir" :129.29, "SteelAng" : -540, "ErrContent" : ""},
		{"Index":265, "x" : 187.204, "y" : 21.088, "z" : 0, "Brake" : 0, "Clutch" : 0, "Accelerat" : 0, "CarDir" :129.29, "SteelAng" : -540, "ErrContent" : ""},
		{"Index":266, "x" : 187.221, "y" : 21.125, "z" : 0, "Brake" : 0, "Clutch" : 0, "Accelerat" : 0, "CarDir" :128.57, "SteelAng" : -540, "ErrContent" : ""},
		{"Index":267, "x" : 187.221, "y" : 21.125, "z" : 0, "Brake" : 0, "Clutch" : 0, "Accelerat" : 0, "CarDir" :128.57, "SteelAng" : -540, "ErrContent" : ""},
		{"Index":268, "x" : 187.221, "y" : 21.125, "z" : 0, "Brake" : 0, "Clutch" : 0, "Accelerat" : 0, "CarDir" :128.57, "SteelAng" : -540, "ErrContent" : ""},
		{"Index":269, "x" : 187.221, "y" : 21.125, "z" : 0, "Brake" : 0, "Clutch" : 0, "Accelerat" : 0, "CarDir" :128.57, "SteelAng" : -540, "ErrContent" : ""},
		{"Index":270, "x" : 187.221, "y" : 21.125, "z" : 0, "Brake" : 0, "Clutch" : 0, "Accelerat" : 0, "CarDir" :128.57, "SteelAng" : -540, "ErrContent" : ""},
		{"Index":271, "x" : 187.221, "y" : 21.125, "z" : 0, "Brake" : 0, "Clutch" : 0, "Accelerat" : 0, "CarDir" :128.57, "SteelAng" : -540, "ErrContent" : ""},
		{"Index":272, "x" : 187.221, "y" : 21.125, "z" : 0, "Brake" : 0, "Clutch" : 0, "Accelerat" : 0, "CarDir" :128.57, "SteelAng" : -540, "ErrContent" : ""},
		{"Index":273, "x" : 187.266, "y" : 21.217, "z" : 0, "Brake" : 0, "Clutch" : 0, "Accelerat" : 0, "CarDir" :126.77, "SteelAng" : -540, "ErrContent" : ""},
		{"Index":274, "x" : 187.266, "y" : 21.217, "z" : 0, "Brake" : 0, "Clutch" : 0, "Accelerat" : 0, "CarDir" :126.77, "SteelAng" : -540, "ErrContent" : ""},
		{"Index":275, "x" : 187.284, "y" : 21.253, "z" : 0, "Brake" : 0, "Clutch" : 0, "Accelerat" : 0, "CarDir" :126.05, "SteelAng" : -540, "ErrContent" : ""},
		{"Index":276, "x" : 187.284, "y" : 21.253, "z" : 0, "Brake" : 0, "Clutch" : 0, "Accelerat" : 0, "CarDir" :126.05, "SteelAng" : -540, "ErrContent" : ""},
		{"Index":277, "x" : 187.284, "y" : 21.253, "z" : 0, "Brake" : 0, "Clutch" : 0, "Accelerat" : 0, "CarDir" :126.05, "SteelAng" : -540, "ErrContent" : ""},
		{"Index":278, "x" : 187.303, "y" : 21.289, "z" : 0, "Brake" : 0, "Clutch" : 0, "Accelerat" : 0, "CarDir" :125.33, "SteelAng" : -540, "ErrContent" : ""},
		{"Index":279, "x" : 187.313, "y" : 21.307, "z" : 0, "Brake" : 0, "Clutch" : 0, "Accelerat" : 0, "CarDir" :124.97, "SteelAng" : -540, "ErrContent" : ""},
		{"Index":280, "x" : 187.322, "y" : 21.325, "z" : 0, "Brake" : 0, "Clutch" : 0, "Accelerat" : 0, "CarDir" :124.61, "SteelAng" : -540, "ErrContent" : ""},
		{"Index":281, "x" : 187.332, "y" : 21.343, "z" : 0, "Brake" : 0, "Clutch" : 0, "Accelerat" : 0, "CarDir" :124.25, "SteelAng" : -540, "ErrContent" : ""},
		{"Index":282, "x" : 187.342, "y" : 21.36, "z" : 0, "Brake" : 0, "Clutch" : 0, "Accelerat" : 0, "CarDir" :123.89, "SteelAng" : -540, "ErrContent" : ""},
		{"Index":283, "x" : 187.342, "y" : 21.36, "z" : 0, "Brake" : 0, "Clutch" : 0, "Accelerat" : 0, "CarDir" :123.89, "SteelAng" : -540, "ErrContent" : ""},
		{"Index":284, "x" : 187.342, "y" : 21.36, "z" : 0, "Brake" : 0, "Clutch" : 0, "Accelerat" : 0, "CarDir" :123.89, "SteelAng" : -540, "ErrContent" : ""},
		{"Index":285, "x" : 187.362, "y" : 21.396, "z" : 0, "Brake" : 0, "Clutch" : 0, "Accelerat" : 0, "CarDir" :123.17, "SteelAng" : -540, "ErrContent" : ""},
		{"Index":286, "x" : 187.362, "y" : 21.396, "z" : 0, "Brake" : 0, "Clutch" : 0, "Accelerat" : 0, "CarDir" :123.17, "SteelAng" : -540, "ErrContent" : ""},
		{"Index":287, "x" : 187.362, "y" : 21.396, "z" : 0, "Brake" : 0, "Clutch" : 0, "Accelerat" : 0, "CarDir" :123.17, "SteelAng" : -540, "ErrContent" : ""},
		{"Index":288, "x" : 187.383, "y" : 21.431, "z" : 0, "Brake" : 0, "Clutch" : 0, "Accelerat" : 0, "CarDir" :122.45, "SteelAng" : -540, "ErrContent" : ""},
		{"Index":289, "x" : 187.383, "y" : 21.431, "z" : 0, "Brake" : 0, "Clutch" : 0, "Accelerat" : 0, "CarDir" :122.45, "SteelAng" : -540, "ErrContent" : ""},
		{"Index":290, "x" : 187.383, "y" : 21.431, "z" : 0, "Brake" : 0, "Clutch" : 0, "Accelerat" : 0, "CarDir" :122.45, "SteelAng" : -540, "ErrContent" : ""},
		{"Index":291, "x" : 187.383, "y" : 21.431, "z" : 0, "Brake" : 0, "Clutch" : 0, "Accelerat" : 0, "CarDir" :122.45, "SteelAng" : -540, "ErrContent" : ""},
		{"Index":292, "x" : 187.414, "y" : 21.483, "z" : 0, "Brake" : 0, "Clutch" : 0, "Accelerat" : 0, "CarDir" :121.37, "SteelAng" : -540, "ErrContent" : ""},
		{"Index":293, "x" : 187.414, "y" : 21.483, "z" : 0, "Brake" : 0, "Clutch" : 0, "Accelerat" : 0, "CarDir" :121.37, "SteelAng" : -540, "ErrContent" : ""},
		{"Index":294, "x" : 187.414, "y" : 21.483, "z" : 0, "Brake" : 0, "Clutch" : 0, "Accelerat" : 0, "CarDir" :121.37, "SteelAng" : -540, "ErrContent" : ""},
		{"Index":295, "x" : 187.447, "y" : 21.534, "z" : 0, "Brake" : 0, "Clutch" : 0, "Accelerat" : 0, "CarDir" :120.28, "SteelAng" : -540, "ErrContent" : ""},
		{"Index":296, "x" : 187.458, "y" : 21.551, "z" : 0, "Brake" : 0, "Clutch" : 0, "Accelerat" : 0, "CarDir" :119.92, "SteelAng" : -540, "ErrContent" : ""},
		{"Index":297, "x" : 187.469, "y" : 21.568, "z" : 0, "Brake" : 0, "Clutch" : 0, "Accelerat" : 0, "CarDir" :119.56, "SteelAng" : -540, "ErrContent" : ""},
		{"Index":298, "x" : 187.469, "y" : 21.568, "z" : 0, "Brake" : 0, "Clutch" : 0, "Accelerat" : 0, "CarDir" :119.56, "SteelAng" : -540, "ErrContent" : ""},
		{"Index":299, "x" : 187.469, "y" : 21.568, "z" : 0, "Brake" : 0, "Clutch" : 0, "Accelerat" : 0, "CarDir" :119.56, "SteelAng" : -540, "ErrContent" : ""},
		{"Index":300, "x" : 187.469, "y" : 21.568, "z" : 0, "Brake" : 0, "Clutch" : 0, "Accelerat" : 0, "CarDir" :119.56, "SteelAng" : -540, "ErrContent" : ""},
		{"Index":301, "x" : 187.469, "y" : 21.568, "z" : 0, "Brake" : 0, "Clutch" : 0, "Accelerat" : 0, "CarDir" :119.56, "SteelAng" : -540, "ErrContent" : ""},
		{"Index":302, "x" : 187.514, "y" : 21.634, "z" : 0, "Brake" : 0, "Clutch" : 0, "Accelerat" : 0, "CarDir" :118.12, "SteelAng" : -540, "ErrContent" : ""},
		{"Index":303, "x" : 187.514, "y" : 21.634, "z" : 0, "Brake" : 0, "Clutch" : 0, "Accelerat" : 0, "CarDir" :118.12, "SteelAng" : -540, "ErrContent" : ""},
		{"Index":304, "x" : 187.526, "y" : 21.651, "z" : 0, "Brake" : 0, "Clutch" : 0, "Accelerat" : 0, "CarDir" :117.76, "SteelAng" : -540, "ErrContent" : ""},
		{"Index":305, "x" : 187.537, "y" : 21.667, "z" : 0, "Brake" : 0, "Clutch" : 0, "Accelerat" : 0, "CarDir" :117.4, "SteelAng" : -540, "ErrContent" : ""},
		{"Index":306, "x" : 187.549, "y" : 21.683, "z" : 0, "Brake" : 0, "Clutch" : 0, "Accelerat" : 0, "CarDir" :117.04, "SteelAng" : -540, "ErrContent" : ""},
		{"Index":307, "x" : 187.561, "y" : 21.7, "z" : 0, "Brake" : 0, "Clutch" : 0, "Accelerat" : 0, "CarDir" :116.68, "SteelAng" : -540, "ErrContent" : ""},
		{"Index":308, "x" : 187.561, "y" : 21.7, "z" : 0, "Brake" : 0, "Clutch" : 0, "Accelerat" : 0, "CarDir" :116.68, "SteelAng" : -540, "ErrContent" : ""},
		{"Index":309, "x" : 187.597, "y" : 21.748, "z" : 0, "Brake" : 0, "Clutch" : 0, "Accelerat" : 0, "CarDir" :115.6, "SteelAng" : -540, "ErrContent" : ""},
		{"Index":310, "x" : 187.597, "y" : 21.748, "z" : 0, "Brake" : 0, "Clutch" : 0, "Accelerat" : 0, "CarDir" :115.6, "SteelAng" : -540, "ErrContent" : ""},
		{"Index":311, "x" : 187.597, "y" : 21.748, "z" : 0, "Brake" : 0, "Clutch" : 0, "Accelerat" : 0, "CarDir" :115.6, "SteelAng" : -540, "ErrContent" : ""},
		{"Index":312, "x" : 187.634, "y" : 21.795, "z" : 0, "Brake" : 0, "Clutch" : 0, "Accelerat" : 0, "CarDir" :114.52, "SteelAng" : -540, "ErrContent" : ""},
		{"Index":313, "x" : 187.646, "y" : 21.811, "z" : 0, "Brake" : 0, "Clutch" : 0, "Accelerat" : 0, "CarDir" :114.16, "SteelAng" : -540, "ErrContent" : ""},
		{"Index":314, "x" : 187.659, "y" : 21.826, "z" : 0, "Brake" : 0, "Clutch" : 0, "Accelerat" : 0, "CarDir" :113.8, "SteelAng" : -540, "ErrContent" : ""},
		{"Index":315, "x" : 187.671, "y" : 21.841, "z" : 0, "Brake" : 0, "Clutch" : 0, "Accelerat" : 0, "CarDir" :113.44, "SteelAng" : -540, "ErrContent" : ""},
		{"Index":316, "x" : 187.671, "y" : 21.841, "z" : 0, "Brake" : 0, "Clutch" : 0, "Accelerat" : 0, "CarDir" :113.44, "SteelAng" : -540, "ErrContent" : ""},
		{"Index":317, "x" : 187.697, "y" : 21.872, "z" : 0, "Brake" : 0, "Clutch" : 0, "Accelerat" : 0, "CarDir" :112.72, "SteelAng" : -540, "ErrContent" : ""},
		{"Index":318, "x" : 187.71, "y" : 21.887, "z" : 0, "Brake" : 0, "Clutch" : 0, "Accelerat" : 0, "CarDir" :112.36, "SteelAng" : -540, "ErrContent" : ""},
		{"Index":319, "x" : 187.723, "y" : 21.902, "z" : 0, "Brake" : 0, "Clutch" : 0, "Accelerat" : 0, "CarDir" :112, "SteelAng" : -540, "ErrContent" : ""},
		{"Index":320, "x" : 187.736, "y" : 21.917, "z" : 0, "Brake" : 0, "Clutch" : 0, "Accelerat" : 0, "CarDir" :111.64, "SteelAng" : -540, "ErrContent" : ""},
		{"Index":321, "x" : 187.736, "y" : 21.917, "z" : 0, "Brake" : 0, "Clutch" : 0, "Accelerat" : 0, "CarDir" :111.64, "SteelAng" : -540, "ErrContent" : ""},
		{"Index":322, "x" : 187.763, "y" : 21.946, "z" : 0, "Brake" : 0, "Clutch" : 0, "Accelerat" : 0, "CarDir" :110.92, "SteelAng" : -540, "ErrContent" : ""},
		{"Index":323, "x" : 187.776, "y" : 21.961, "z" : 0, "Brake" : 0, "Clutch" : 0, "Accelerat" : 0, "CarDir" :110.56, "SteelAng" : -540, "ErrContent" : ""},
		{"Index":324, "x" : 187.817, "y" : 22.004, "z" : 0, "Brake" : 0, "Clutch" : 0, "Accelerat" : 0, "CarDir" :109.48, "SteelAng" : -540, "ErrContent" : ""},
		{"Index":325, "x" : 187.83, "y" : 22.018, "z" : 0, "Brake" : 0, "Clutch" : 0, "Accelerat" : 0, "CarDir" :109.12, "SteelAng" : -530, "ErrContent" : ""},
		{"Index":326, "x" : 187.83, "y" : 22.018, "z" : 0, "Brake" : 0, "Clutch" : 0, "Accelerat" : 0, "CarDir" :109.12, "SteelAng" : -530, "ErrContent" : ""},
		{"Index":327, "x" : 187.83, "y" : 22.018, "z" : 0, "Brake" : 0, "Clutch" : 0, "Accelerat" : 0, "CarDir" :109.12, "SteelAng" : -530, "ErrContent" : ""},
		{"Index":328, "x" : 187.83, "y" : 22.018, "z" : 0, "Brake" : 0, "Clutch" : 0, "Accelerat" : 0, "CarDir" :109.12, "SteelAng" : -530, "ErrContent" : ""},
		{"Index":329, "x" : 187.872, "y" : 22.06, "z" : 0, "Brake" : 0, "Clutch" : 0, "Accelerat" : 0, "CarDir" :108.06, "SteelAng" : -530, "ErrContent" : ""},
		{"Index":330, "x" : 187.872, "y" : 22.06, "z" : 0, "Brake" : 0, "Clutch" : 0, "Accelerat" : 0, "CarDir" :108.06, "SteelAng" : -530, "ErrContent" : ""},
		{"Index":331, "x" : 187.901, "y" : 22.087, "z" : 0, "Brake" : 0, "Clutch" : 0, "Accelerat" : 0, "CarDir" :107.36, "SteelAng" : -530, "ErrContent" : ""},
		{"Index":332, "x" : 187.901, "y" : 22.087, "z" : 0, "Brake" : 0, "Clutch" : 0, "Accelerat" : 0, "CarDir" :107.36, "SteelAng" : -530, "ErrContent" : ""},
		{"Index":333, "x" : 187.929, "y" : 22.113, "z" : 0, "Brake" : 0, "Clutch" : 0, "Accelerat" : 0, "CarDir" :106.66, "SteelAng" : -530, "ErrContent" : ""},
		{"Index":334, "x" : 187.944, "y" : 22.126, "z" : 0, "Brake" : 0, "Clutch" : 0, "Accelerat" : 0, "CarDir" :106.31, "SteelAng" : -530, "ErrContent" : ""},
		{"Index":335, "x" : 187.944, "y" : 22.126, "z" : 0, "Brake" : 0, "Clutch" : 0, "Accelerat" : 0, "CarDir" :106.31, "SteelAng" : -520, "ErrContent" : ""},
		{"Index":336, "x" : 187.973, "y" : 22.152, "z" : 0, "Brake" : 0, "Clutch" : 0, "Accelerat" : 0, "CarDir" :105.62, "SteelAng" : -520, "ErrContent" : ""},
		{"Index":337, "x" : 187.973, "y" : 22.152, "z" : 0, "Brake" : 0, "Clutch" : 0, "Accelerat" : 0, "CarDir" :105.62, "SteelAng" : -520, "ErrContent" : ""},
		{"Index":338, "x" : 187.973, "y" : 22.152, "z" : 0, "Brake" : 0, "Clutch" : 0, "Accelerat" : 0, "CarDir" :105.62, "SteelAng" : -520, "ErrContent" : ""},
		{"Index":339, "x" : 187.973, "y" : 22.152, "z" : 0, "Brake" : 0, "Clutch" : 0, "Accelerat" : 0, "CarDir" :105.62, "SteelAng" : -520, "ErrContent" : ""},
		{"Index":340, "x" : 187.973, "y" : 22.152, "z" : 0, "Brake" : 0, "Clutch" : 0, "Accelerat" : 0, "CarDir" :105.62, "SteelAng" : -520, "ErrContent" : ""},
		{"Index":341, "x" : 187.973, "y" : 22.152, "z" : 0, "Brake" : 0, "Clutch" : 0, "Accelerat" : 0, "CarDir" :105.62, "SteelAng" : -520, "ErrContent" : ""},
		{"Index":342, "x" : 188.094, "y" : 22.25, "z" : 0, "Brake" : 0, "Clutch" : 0, "Accelerat" : 0, "CarDir" :102.88, "SteelAng" : -520, "ErrContent" : ""},
		{"Index":343, "x" : 188.094, "y" : 22.25, "z" : 0, "Brake" : 0, "Clutch" : 0, "Accelerat" : 0, "CarDir" :102.88, "SteelAng" : -520, "ErrContent" : ""},
		{"Index":344, "x" : 188.125, "y" : 22.273, "z" : 0, "Brake" : 0, "Clutch" : 0, "Accelerat" : 0, "CarDir" :102.21, "SteelAng" : -490, "ErrContent" : ""},
		{"Index":345, "x" : 188.141, "y" : 22.284, "z" : 0, "Brake" : 0, "Clutch" : 0, "Accelerat" : 0, "CarDir" :101.9, "SteelAng" : -480, "ErrContent" : ""},
		{"Index":346, "x" : 188.158, "y" : 22.295, "z" : 0, "Brake" : 0, "Clutch" : 0, "Accelerat" : 0, "CarDir" :101.59, "SteelAng" : -480, "ErrContent" : ""},
		{"Index":347, "x" : 188.174, "y" : 22.305, "z" : 0, "Brake" : 0, "Clutch" : 0, "Accelerat" : 0, "CarDir" :101.3, "SteelAng" : -450, "ErrContent" : ""},
		{"Index":348, "x" : 188.174, "y" : 22.305, "z" : 0, "Brake" : 0, "Clutch" : 0, "Accelerat" : 0, "CarDir" :101.3, "SteelAng" : -430, "ErrContent" : ""},
		{"Index":349, "x" : 188.174, "y" : 22.305, "z" : 0, "Brake" : 0, "Clutch" : 0, "Accelerat" : 0, "CarDir" :101.3, "SteelAng" : -420, "ErrContent" : ""},
		{"Index":350, "x" : 188.225, "y" : 22.334, "z" : 0, "Brake" : 0, "Clutch" : 0, "Accelerat" : 0, "CarDir" :100.5, "SteelAng" : -400, "ErrContent" : ""},
		{"Index":351, "x" : 188.242, "y" : 22.343, "z" : 0, "Brake" : 0, "Clutch" : 0, "Accelerat" : 0, "CarDir" :100.26, "SteelAng" : -390, "ErrContent" : ""},
		{"Index":352, "x" : 188.242, "y" : 22.343, "z" : 0, "Brake" : 0, "Clutch" : 0, "Accelerat" : 0, "CarDir" :100.26, "SteelAng" : -370, "ErrContent" : ""},
		{"Index":353, "x" : 188.242, "y" : 22.343, "z" : 0, "Brake" : 0, "Clutch" : 0, "Accelerat" : 0, "CarDir" :100.26, "SteelAng" : -360, "ErrContent" : ""},
		{"Index":354, "x" : 188.242, "y" : 22.343, "z" : 0, "Brake" : 0, "Clutch" : 0, "Accelerat" : 0, "CarDir" :100.26, "SteelAng" : -360, "ErrContent" : ""},
		{"Index":355, "x" : 188.242, "y" : 22.343, "z" : 0, "Brake" : 0, "Clutch" : 0, "Accelerat" : 0, "CarDir" :100.26, "SteelAng" : -360, "ErrContent" : ""},
		{"Index":356, "x" : 188.242, "y" : 22.343, "z" : 0, "Brake" : 0, "Clutch" : 0, "Accelerat" : 0, "CarDir" :100.26, "SteelAng" : -360, "ErrContent" : ""},
		{"Index":357, "x" : 188.331, "y" : 22.383, "z" : 0, "Brake" : 0, "Clutch" : 0, "Accelerat" : 0, "CarDir" :99.17, "SteelAng" : -360, "ErrContent" : ""},
		{"Index":358, "x" : 188.331, "y" : 22.383, "z" : 0, "Brake" : 0, "Clutch" : 0, "Accelerat" : 0, "CarDir" :99.17, "SteelAng" : -360, "ErrContent" : ""},
		{"Index":359, "x" : 188.331, "y" : 22.383, "z" : 0, "Brake" : 0, "Clutch" : 0, "Accelerat" : 0, "CarDir" :99.17, "SteelAng" : -360, "ErrContent" : ""},
		{"Index":360, "x" : 188.384, "y" : 22.406, "z" : 0, "Brake" : 0, "Clutch" : 0, "Accelerat" : 0, "CarDir" :98.54, "SteelAng" : -360, "ErrContent" : ""},
		{"Index":361, "x" : 188.384, "y" : 22.406, "z" : 0, "Brake" : 0, "Clutch" : 0, "Accelerat" : 0, "CarDir" :98.54, "SteelAng" : -360, "ErrContent" : ""},
		{"Index":362, "x" : 188.384, "y" : 22.406, "z" : 0, "Brake" : 0, "Clutch" : 0, "Accelerat" : 0, "CarDir" :98.54, "SteelAng" : -360, "ErrContent" : ""},
		{"Index":363, "x" : 188.438, "y" : 22.428, "z" : 0, "Brake" : 0, "Clutch" : 0, "Accelerat" : 0, "CarDir" :97.91, "SteelAng" : -360, "ErrContent" : ""},
		{"Index":364, "x" : 188.438, "y" : 22.428, "z" : 0, "Brake" : 0, "Clutch" : 0, "Accelerat" : 0, "CarDir" :97.91, "SteelAng" : -360, "ErrContent" : ""},
		{"Index":365, "x" : 188.438, "y" : 22.428, "z" : 0, "Brake" : 0, "Clutch" : 0, "Accelerat" : 0, "CarDir" :97.91, "SteelAng" : -360, "ErrContent" : ""},
		{"Index":366, "x" : 188.438, "y" : 22.428, "z" : 0, "Brake" : 0, "Clutch" : 0, "Accelerat" : 0, "CarDir" :97.91, "SteelAng" : -360, "ErrContent" : ""},
		{"Index":367, "x" : 188.511, "y" : 22.457, "z" : 0, "Brake" : 0, "Clutch" : 0, "Accelerat" : 0, "CarDir" :97.06, "SteelAng" : -360, "ErrContent" : ""},
		{"Index":368, "x" : 188.529, "y" : 22.464, "z" : 0, "Brake" : 0, "Clutch" : 0, "Accelerat" : 0, "CarDir" :96.85, "SteelAng" : -360, "ErrContent" : ""},
		{"Index":369, "x" : 188.529, "y" : 22.464, "z" : 0, "Brake" : 0, "Clutch" : 0, "Accelerat" : 0, "CarDir" :96.85, "SteelAng" : -360, "ErrContent" : ""},
		{"Index":370, "x" : 188.565, "y" : 22.477, "z" : 0, "Brake" : 0, "Clutch" : 0, "Accelerat" : 0, "CarDir" :96.43, "SteelAng" : -360, "ErrContent" : ""},
		{"Index":371, "x" : 188.583, "y" : 22.484, "z" : 0, "Brake" : 0, "Clutch" : 0, "Accelerat" : 0, "CarDir" :96.22, "SteelAng" : -360, "ErrContent" : ""},
		{"Index":372, "x" : 188.601, "y" : 22.49, "z" : 0, "Brake" : 0, "Clutch" : 0, "Accelerat" : 0, "CarDir" :96.01, "SteelAng" : -360, "ErrContent" : ""},
		{"Index":373, "x" : 188.601, "y" : 22.49, "z" : 0, "Brake" : 0, "Clutch" : 0, "Accelerat" : 0, "CarDir" :96.01, "SteelAng" : -360, "ErrContent" : ""},
		{"Index":374, "x" : 188.62, "y" : 22.496, "z" : 0, "Brake" : 0, "Clutch" : 0, "Accelerat" : 0, "CarDir" :95.79, "SteelAng" : -360, "ErrContent" : ""},
		{"Index":375, "x" : 188.638, "y" : 22.503, "z" : 0, "Brake" : 0, "Clutch" : 0, "Accelerat" : 0, "CarDir" :95.58, "SteelAng" : -360, "ErrContent" : ""},
		{"Index":376, "x" : 188.656, "y" : 22.509, "z" : 0, "Brake" : 0, "Clutch" : 0, "Accelerat" : 0, "CarDir" :95.37, "SteelAng" : -360, "ErrContent" : ""},
		{"Index":377, "x" : 188.675, "y" : 22.515, "z" : 0, "Brake" : 0, "Clutch" : 0, "Accelerat" : 0, "CarDir" :95.16, "SteelAng" : -360, "ErrContent" : ""},
		{"Index":378, "x" : 188.693, "y" : 22.521, "z" : 0, "Brake" : 0, "Clutch" : 0, "Accelerat" : 0, "CarDir" :94.95, "SteelAng" : -360, "ErrContent" : ""},
		{"Index":379, "x" : 188.693, "y" : 22.521, "z" : 0, "Brake" : 0, "Clutch" : 0, "Accelerat" : 0, "CarDir" :94.95, "SteelAng" : -360, "ErrContent" : ""},
		{"Index":380, "x" : 188.693, "y" : 22.521, "z" : 0, "Brake" : 0, "Clutch" : 0, "Accelerat" : 0, "CarDir" :94.95, "SteelAng" : -360, "ErrContent" : ""},
		{"Index":381, "x" : 188.748, "y" : 22.538, "z" : 0, "Brake" : 0, "Clutch" : 0, "Accelerat" : 0, "CarDir" :94.32, "SteelAng" : -360, "ErrContent" : ""},
		{"Index":382, "x" : 188.767, "y" : 22.544, "z" : 0, "Brake" : 0, "Clutch" : 0, "Accelerat" : 0, "CarDir" :94.1, "SteelAng" : -360, "ErrContent" : ""},
		{"Index":383, "x" : 188.785, "y" : 22.55, "z" : 0, "Brake" : 0, "Clutch" : 0, "Accelerat" : 0, "CarDir" :93.89, "SteelAng" : -360, "ErrContent" : ""},
		{"Index":384, "x" : 188.785, "y" : 22.55, "z" : 0, "Brake" : 0, "Clutch" : 0, "Accelerat" : 0, "CarDir" :93.89, "SteelAng" : -360, "ErrContent" : ""},
		{"Index":385, "x" : 188.822, "y" : 22.561, "z" : 0, "Brake" : 0, "Clutch" : 0, "Accelerat" : 0, "CarDir" :93.47, "SteelAng" : 0, "ErrContent" : ""},
		{"Index":386, "x" : 188.862, "y" : 22.563, "z" : 0, "Brake" : 0, "Clutch" : 0, "Accelerat" : 0, "CarDir" :93.47, "SteelAng" : 0, "ErrContent" : ""},
		{"Index":387, "x" : 188.862, "y" : 22.563, "z" : 0, "Brake" : 0, "Clutch" : 0, "Accelerat" : 0, "CarDir" :93.47, "SteelAng" : 0, "ErrContent" : ""},
		{"Index":388, "x" : 188.902, "y" : 22.565, "z" : 0, "Brake" : 0, "Clutch" : 0, "Accelerat" : 0, "CarDir" :93.47, "SteelAng" : 0, "ErrContent" : ""},
		{"Index":389, "x" : 188.922, "y" : 22.567, "z" : 0, "Brake" : 0, "Clutch" : 0, "Accelerat" : 0, "CarDir" :93.47, "SteelAng" : 0, "ErrContent" : ""},
		{"Index":390, "x" : 188.922, "y" : 22.567, "z" : 0, "Brake" : 0, "Clutch" : 0, "Accelerat" : 0, "CarDir" :93.47, "SteelAng" : 0, "ErrContent" : ""},
		{"Index":391, "x" : 188.922, "y" : 22.567, "z" : 0, "Brake" : 0, "Clutch" : 0, "Accelerat" : 0, "CarDir" :93.47, "SteelAng" : 0, "ErrContent" : ""},
		{"Index":392, "x" : 188.922, "y" : 22.567, "z" : 0, "Brake" : 0, "Clutch" : 0, "Accelerat" : 0, "CarDir" :93.47, "SteelAng" : 0, "ErrContent" : ""},
		{"Index":393, "x" : 188.922, "y" : 22.567, "z" : 0, "Brake" : 0, "Clutch" : 0, "Accelerat" : 0, "CarDir" :93.47, "SteelAng" : 0, "ErrContent" : ""},
		{"Index":394, "x" : 189.062, "y" : 22.575, "z" : 0, "Brake" : 0, "Clutch" : 0, "Accelerat" : 0, "CarDir" :93.47, "SteelAng" : 0, "ErrContent" : ""},
		{"Index":395, "x" : 189.082, "y" : 22.576, "z" : 0, "Brake" : 0, "Clutch" : 0, "Accelerat" : 0, "CarDir" :93.47, "SteelAng" : 0, "ErrContent" : ""},
		{"Index":396, "x" : 189.122, "y" : 22.579, "z" : 0, "Brake" : 0, "Clutch" : 0, "Accelerat" : 0, "CarDir" :93.47, "SteelAng" : 0, "ErrContent" : ""},
		{"Index":397, "x" : 189.142, "y" : 22.58, "z" : 0, "Brake" : 0, "Clutch" : 0, "Accelerat" : 0, "CarDir" :93.47, "SteelAng" : 0, "ErrContent" : ""},
		{"Index":398, "x" : 189.162, "y" : 22.581, "z" : 0, "Brake" : 0, "Clutch" : 0, "Accelerat" : 0, "CarDir" :93.47, "SteelAng" : 0, "ErrContent" : ""},
		{"Index":399, "x" : 189.162, "y" : 22.581, "z" : 0, "Brake" : 0, "Clutch" : 0, "Accelerat" : 0, "CarDir" :93.47, "SteelAng" : 0, "ErrContent" : ""},
		{"Index":400, "x" : 189.202, "y" : 22.584, "z" : 0, "Brake" : 0, "Clutch" : 0, "Accelerat" : 0, "CarDir" :93.47, "SteelAng" : 0, "ErrContent" : ""},
		{"Index":401, "x" : 189.222, "y" : 22.585, "z" : 0, "Brake" : 0, "Clutch" : 0, "Accelerat" : 0, "CarDir" :93.47, "SteelAng" : 0, "ErrContent" : ""},
		{"Index":402, "x" : 189.261, "y" : 22.587, "z" : 0, "Brake" : 0, "Clutch" : 0, "Accelerat" : 0, "CarDir" :93.47, "SteelAng" : 0, "ErrContent" : ""},
		{"Index":403, "x" : 189.281, "y" : 22.588, "z" : 0, "Brake" : 0, "Clutch" : 0, "Accelerat" : 0, "CarDir" :93.47, "SteelAng" : 0, "ErrContent" : ""},
		{"Index":404, "x" : 189.301, "y" : 22.59, "z" : 0, "Brake" : 0, "Clutch" : 0, "Accelerat" : 0, "CarDir" :93.47, "SteelAng" : 0, "ErrContent" : ""},
		{"Index":405, "x" : 189.321, "y" : 22.591, "z" : 0, "Brake" : 0, "Clutch" : 0, "Accelerat" : 0, "CarDir" :93.47, "SteelAng" : 0, "ErrContent" : ""},
		{"Index":406, "x" : 189.341, "y" : 22.592, "z" : 0, "Brake" : 0, "Clutch" : 0, "Accelerat" : 0, "CarDir" :93.47, "SteelAng" : 0, "ErrContent" : ""},
		{"Index":407, "x" : 189.361, "y" : 22.593, "z" : 0, "Brake" : 0, "Clutch" : 0, "Accelerat" : 0, "CarDir" :93.47, "SteelAng" : 0, "ErrContent" : ""},
		{"Index":408, "x" : 189.401, "y" : 22.596, "z" : 0, "Brake" : 0, "Clutch" : 0, "Accelerat" : 0, "CarDir" :93.47, "SteelAng" : 0, "ErrContent" : ""},
		{"Index":409, "x" : 189.421, "y" : 22.597, "z" : 0, "Brake" : 0, "Clutch" : 0, "Accelerat" : 0, "CarDir" :93.47, "SteelAng" : 0, "ErrContent" : ""},
		{"Index":410, "x" : 189.421, "y" : 22.597, "z" : 0, "Brake" : 0, "Clutch" : 0, "Accelerat" : 0, "CarDir" :93.47, "SteelAng" : 0, "ErrContent" : ""},
		{"Index":411, "x" : 189.421, "y" : 22.597, "z" : 0, "Brake" : 0, "Clutch" : 0, "Accelerat" : 0, "CarDir" :93.47, "SteelAng" : 0, "ErrContent" : ""},
		{"Index":412, "x" : 189.481, "y" : 22.6, "z" : 0, "Brake" : 0, "Clutch" : 0, "Accelerat" : 0, "CarDir" :93.47, "SteelAng" : 0, "ErrContent" : ""},
		{"Index":413, "x" : 189.481, "y" : 22.6, "z" : 0, "Brake" : 0, "Clutch" : 0, "Accelerat" : 0, "CarDir" :93.47, "SteelAng" : 0, "ErrContent" : ""},
		{"Index":414, "x" : 189.621, "y" : 22.609, "z" : 0, "Brake" : 0, "Clutch" : 0, "Accelerat" : 0, "CarDir" :93.47, "SteelAng" : 0, "ErrContent" : ""},
		{"Index":415, "x" : 189.621, "y" : 22.609, "z" : 0, "Brake" : 0, "Clutch" : 0, "Accelerat" : 0, "CarDir" :93.47, "SteelAng" : 0, "ErrContent" : ""},
		{"Index":416, "x" : 189.621, "y" : 22.609, "z" : 0, "Brake" : 0, "Clutch" : 0, "Accelerat" : 0, "CarDir" :93.47, "SteelAng" : -10, "ErrContent" : ""},
		{"Index":417, "x" : 189.681, "y" : 22.612, "z" : 0, "Brake" : 0, "Clutch" : 0, "Accelerat" : 0, "CarDir" :93.47, "SteelAng" : -10, "ErrContent" : ""},
		{"Index":418, "x" : 189.681, "y" : 22.612, "z" : 0, "Brake" : 0, "Clutch" : 0, "Accelerat" : 0, "CarDir" :93.47, "SteelAng" : -10, "ErrContent" : ""},
		{"Index":419, "x" : 189.681, "y" : 22.612, "z" : 0, "Brake" : 0, "Clutch" : 0, "Accelerat" : 0, "CarDir" :93.47, "SteelAng" : -10, "ErrContent" : ""},
		{"Index":420, "x" : 189.681, "y" : 22.612, "z" : 0, "Brake" : 0, "Clutch" : 0, "Accelerat" : 0, "CarDir" :93.47, "SteelAng" : -10, "ErrContent" : ""},
		{"Index":421, "x" : 189.781, "y" : 22.616, "z" : 0, "Brake" : 0, "Clutch" : 0, "Accelerat" : 0, "CarDir" :93.44, "SteelAng" : -10, "ErrContent" : ""},
		{"Index":422, "x" : 189.82, "y" : 22.617, "z" : 0, "Brake" : 0, "Clutch" : 0, "Accelerat" : 0, "CarDir" :93.43, "SteelAng" : -10, "ErrContent" : ""},
		{"Index":423, "x" : 189.82, "y" : 22.617, "z" : 0, "Brake" : 0, "Clutch" : 0, "Accelerat" : 0, "CarDir" :93.43, "SteelAng" : -10, "ErrContent" : ""},
		{"Index":424, "x" : 189.86, "y" : 22.619, "z" : 0, "Brake" : 0, "Clutch" : 0, "Accelerat" : 0, "CarDir" :93.42, "SteelAng" : -20, "ErrContent" : ""},
		{"Index":425, "x" : 189.86, "y" : 22.619, "z" : 0, "Brake" : 0, "Clutch" : 0, "Accelerat" : 0, "CarDir" :93.42, "SteelAng" : -40, "ErrContent" : ""},
		{"Index":426, "x" : 189.92, "y" : 22.622, "z" : 0, "Brake" : 0, "Clutch" : 0, "Accelerat" : 0, "CarDir" :93.37, "SteelAng" : -70, "ErrContent" : ""},
		{"Index":427, "x" : 189.94, "y" : 22.623, "z" : 0, "Brake" : 0, "Clutch" : 0, "Accelerat" : 0, "CarDir" :93.33, "SteelAng" : -80, "ErrContent" : ""},
		{"Index":428, "x" : 189.96, "y" : 22.624, "z" : 0, "Brake" : 0, "Clutch" : 0, "Accelerat" : 0, "CarDir" :93.29, "SteelAng" : -110, "ErrContent" : ""},
		{"Index":429, "x" : 189.999, "y" : 22.628, "z" : 0, "Brake" : 0, "Clutch" : 0, "Accelerat" : 0, "CarDir" :93.18, "SteelAng" : -130, "ErrContent" : ""},
		{"Index":430, "x" : 190.039, "y" : 22.632, "z" : 0, "Brake" : 0, "Clutch" : 0, "Accelerat" : 0, "CarDir" :93.05, "SteelAng" : -140, "ErrContent" : ""},
		{"Index":431, "x" : 190.078, "y" : 22.636, "z" : 0, "Brake" : 0, "Clutch" : 0, "Accelerat" : 0, "CarDir" :92.9, "SteelAng" : -140, "ErrContent" : ""},
		{"Index":432, "x" : 190.117, "y" : 22.64, "z" : 0, "Brake" : 0, "Clutch" : 0, "Accelerat" : 0, "CarDir" :92.75, "SteelAng" : -130, "ErrContent" : ""},
		{"Index":433, "x" : 190.137, "y" : 22.641, "z" : 0, "Brake" : 0, "Clutch" : 0, "Accelerat" : 0, "CarDir" :92.69, "SteelAng" : -130, "ErrContent" : ""},
		{"Index":434, "x" : 190.176, "y" : 22.645, "z" : 0, "Brake" : 0, "Clutch" : 0, "Accelerat" : 0, "CarDir" :92.55, "SteelAng" : -130, "ErrContent" : ""},
		{"Index":435, "x" : 190.216, "y" : 22.648, "z" : 0, "Brake" : 0, "Clutch" : 0, "Accelerat" : 0, "CarDir" :92.42, "SteelAng" : -130, "ErrContent" : ""},
		{"Index":436, "x" : 190.255, "y" : 22.651, "z" : 0, "Brake" : 0, "Clutch" : 0, "Accelerat" : 0, "CarDir" :92.28, "SteelAng" : -130, "ErrContent" : ""},
		{"Index":437, "x" : 190.294, "y" : 22.654, "z" : 0, "Brake" : 0, "Clutch" : 0, "Accelerat" : 0, "CarDir" :92.15, "SteelAng" : -130, "ErrContent" : ""},
		{"Index":438, "x" : 190.354, "y" : 22.658, "z" : 0, "Brake" : 0, "Clutch" : 0, "Accelerat" : 0, "CarDir" :91.97, "SteelAng" : -90, "ErrContent" : ""},
		{"Index":439, "x" : 190.374, "y" : 22.659, "z" : 0, "Brake" : 0, "Clutch" : 0, "Accelerat" : 0, "CarDir" :91.92, "SteelAng" : -80, "ErrContent" : ""},
		{"Index":440, "x" : 190.393, "y" : 22.66, "z" : 0, "Brake" : 0, "Clutch" : 0, "Accelerat" : 0, "CarDir" :91.88, "SteelAng" : -60, "ErrContent" : ""},
		{"Index":441, "x" : 190.393, "y" : 22.66, "z" : 0, "Brake" : 0, "Clutch" : 0, "Accelerat" : 0, "CarDir" :91.88, "SteelAng" : -60, "ErrContent" : ""},
		{"Index":442, "x" : 190.393, "y" : 22.66, "z" : 0, "Brake" : 0, "Clutch" : 0, "Accelerat" : 0, "CarDir" :91.88, "SteelAng" : -60, "ErrContent" : ""},
		{"Index":443, "x" : 190.413, "y" : 22.661, "z" : 0, "Brake" : 0, "Clutch" : 0, "Accelerat" : 0, "CarDir" :91.85, "SteelAng" : -50, "ErrContent" : ""},
		{"Index":444, "x" : 190.453, "y" : 22.661, "z" : 0, "Brake" : 0, "Clutch" : 0, "Accelerat" : 0, "CarDir" :91.81, "SteelAng" : -10, "ErrContent" : ""},
		{"Index":445, "x" : 190.473, "y" : 22.661, "z" : 0, "Brake" : 0, "Clutch" : 0, "Accelerat" : 0, "CarDir" :91.81, "SteelAng" : 20, "ErrContent" : ""},
		{"Index":446, "x" : 190.513, "y" : 22.661, "z" : 0, "Brake" : 0, "Clutch" : 0, "Accelerat" : 0, "CarDir" :91.81, "SteelAng" : 30, "ErrContent" : ""},
		{"Index":447, "x" : 190.533, "y" : 22.661, "z" : 0, "Brake" : 0, "Clutch" : 0, "Accelerat" : 0, "CarDir" :91.83, "SteelAng" : 50, "ErrContent" : ""},
		{"Index":448, "x" : 190.533, "y" : 22.661, "z" : 0, "Brake" : 0, "Clutch" : 0, "Accelerat" : 0, "CarDir" :91.83, "SteelAng" : 60, "ErrContent" : ""},
		{"Index":449, "x" : 190.573, "y" : 22.659, "z" : 0, "Brake" : 0, "Clutch" : 0, "Accelerat" : 0, "CarDir" :91.88, "SteelAng" : 80, "ErrContent" : ""},
		{"Index":450, "x" : 190.613, "y" : 22.657, "z" : 0, "Brake" : 0, "Clutch" : 0, "Accelerat" : 0, "CarDir" :91.97, "SteelAng" : 110, "ErrContent" : ""},
		{"Index":451, "x" : 190.633, "y" : 22.656, "z" : 0, "Brake" : 0, "Clutch" : 0, "Accelerat" : 0, "CarDir" :92.03, "SteelAng" : 120, "ErrContent" : ""},
		{"Index":452, "x" : 190.633, "y" : 22.656, "z" : 0, "Brake" : 0, "Clutch" : 0, "Accelerat" : 0, "CarDir" :92.03, "SteelAng" : 150, "ErrContent" : ""},
		{"Index":453, "x" : 190.633, "y" : 22.656, "z" : 0, "Brake" : 0, "Clutch" : 0, "Accelerat" : 0, "CarDir" :92.03, "SteelAng" : 170, "ErrContent" : ""},
		{"Index":454, "x" : 190.633, "y" : 22.656, "z" : 0, "Brake" : 0, "Clutch" : 0, "Accelerat" : 0, "CarDir" :92.03, "SteelAng" : 200, "ErrContent" : ""},
		{"Index":455, "x" : 190.751, "y" : 22.645, "z" : 0, "Brake" : 0, "Clutch" : 0, "Accelerat" : 0, "CarDir" :92.53, "SteelAng" : 210, "ErrContent" : ""},
		{"Index":456, "x" : 190.771, "y" : 22.642, "z" : 0, "Brake" : 0, "Clutch" : 0, "Accelerat" : 0, "CarDir" :92.64, "SteelAng" : 230, "ErrContent" : ""},
		{"Index":457, "x" : 190.79, "y" : 22.64, "z" : 0, "Brake" : 0, "Clutch" : 0, "Accelerat" : 0, "CarDir" :92.77, "SteelAng" : 240, "ErrContent" : ""},
		{"Index":458, "x" : 190.79, "y" : 22.64, "z" : 0, "Brake" : 0, "Clutch" : 0, "Accelerat" : 0, "CarDir" :92.77, "SteelAng" : 250, "ErrContent" : ""},
		{"Index":459, "x" : 190.83, "y" : 22.635, "z" : 0, "Brake" : 0, "Clutch" : 0, "Accelerat" : 0, "CarDir" :93.04, "SteelAng" : 280, "ErrContent" : ""},
		{"Index":460, "x" : 190.83, "y" : 22.635, "z" : 0, "Brake" : 0, "Clutch" : 0, "Accelerat" : 0, "CarDir" :93.04, "SteelAng" : 290, "ErrContent" : ""},
		{"Index":461, "x" : 190.83, "y" : 22.635, "z" : 0, "Brake" : 0, "Clutch" : 0, "Accelerat" : 0, "CarDir" :93.04, "SteelAng" : 300, "ErrContent" : ""},
		{"Index":462, "x" : 190.83, "y" : 22.635, "z" : 0, "Brake" : 0, "Clutch" : 0, "Accelerat" : 0, "CarDir" :93.04, "SteelAng" : 320, "ErrContent" : ""},
		{"Index":463, "x" : 190.907, "y" : 22.622, "z" : 0, "Brake" : 0, "Clutch" : 0, "Accelerat" : 0, "CarDir" :93.71, "SteelAng" : 340, "ErrContent" : ""},
		{"Index":464, "x" : 190.907, "y" : 22.622, "z" : 0, "Brake" : 0, "Clutch" : 0, "Accelerat" : 0, "CarDir" :93.71, "SteelAng" : 350, "ErrContent" : ""},
		{"Index":465, "x" : 190.907, "y" : 22.622, "z" : 0, "Brake" : 0, "Clutch" : 0, "Accelerat" : 0, "CarDir" :93.71, "SteelAng" : 370, "ErrContent" : ""},
		{"Index":466, "x" : 190.907, "y" : 22.622, "z" : 0, "Brake" : 0, "Clutch" : 0, "Accelerat" : 0, "CarDir" :93.71, "SteelAng" : 380, "ErrContent" : ""},
		{"Index":467, "x" : 190.984, "y" : 22.607, "z" : 0, "Brake" : 0, "Clutch" : 0, "Accelerat" : 0, "CarDir" :94.55, "SteelAng" : 400, "ErrContent" : ""},
		{"Index":468, "x" : 191.003, "y" : 22.602, "z" : 0, "Brake" : 0, "Clutch" : 0, "Accelerat" : 0, "CarDir" :94.79, "SteelAng" : 410, "ErrContent" : ""},
		{"Index":469, "x" : 191.003, "y" : 22.602, "z" : 0, "Brake" : 0, "Clutch" : 0, "Accelerat" : 0, "CarDir" :94.79, "SteelAng" : 430, "ErrContent" : ""},
		{"Index":470, "x" : 191.04, "y" : 22.593, "z" : 0, "Brake" : 0, "Clutch" : 0, "Accelerat" : 0, "CarDir" :95.31, "SteelAng" : 440, "ErrContent" : ""},
		{"Index":471, "x" : 191.059, "y" : 22.589, "z" : 0, "Brake" : 0, "Clutch" : 0, "Accelerat" : 0, "CarDir" :95.58, "SteelAng" : 460, "ErrContent" : ""},
		{"Index":472, "x" : 191.078, "y" : 22.584, "z" : 0, "Brake" : 0, "Clutch" : 0, "Accelerat" : 0, "CarDir" :95.87, "SteelAng" : 470, "ErrContent" : ""},
		{"Index":473, "x" : 191.078, "y" : 22.584, "z" : 0, "Brake" : 0, "Clutch" : 0, "Accelerat" : 0, "CarDir" :95.87, "SteelAng" : 490, "ErrContent" : ""},
		{"Index":474, "x" : 191.115, "y" : 22.574, "z" : 0, "Brake" : 0, "Clutch" : 0, "Accelerat" : 0, "CarDir" :96.48, "SteelAng" : 500, "ErrContent" : ""},
		{"Index":475, "x" : 191.133, "y" : 22.569, "z" : 0, "Brake" : 0, "Clutch" : 0, "Accelerat" : 0, "CarDir" :96.81, "SteelAng" : 530, "ErrContent" : ""},
		{"Index":476, "x" : 191.17, "y" : 22.557, "z" : 0, "Brake" : 0, "Clutch" : 0, "Accelerat" : 0, "CarDir" :97.5, "SteelAng" : 540, "ErrContent" : ""},
		{"Index":477, "x" : 191.188, "y" : 22.552, "z" : 0, "Brake" : 0, "Clutch" : 0, "Accelerat" : 0, "CarDir" :97.86, "SteelAng" : 540, "ErrContent" : ""},
		{"Index":478, "x" : 191.188, "y" : 22.552, "z" : 0, "Brake" : 0, "Clutch" : 0, "Accelerat" : 0, "CarDir" :97.86, "SteelAng" : 540, "ErrContent" : ""},
		{"Index":479, "x" : 191.225, "y" : 22.54, "z" : 0, "Brake" : 0, "Clutch" : 0, "Accelerat" : 0, "CarDir" :98.58, "SteelAng" : 540, "ErrContent" : ""},
		{"Index":480, "x" : 191.243, "y" : 22.535, "z" : 0, "Brake" : 0, "Clutch" : 0, "Accelerat" : 0, "CarDir" :98.94, "SteelAng" : 540, "ErrContent" : ""},
		{"Index":481, "x" : 191.261, "y" : 22.53, "z" : 0, "Brake" : 0, "Clutch" : 0, "Accelerat" : 0, "CarDir" :99.3, "SteelAng" : 540, "ErrContent" : ""},
		{"Index":482, "x" : 191.261, "y" : 22.53, "z" : 0, "Brake" : 0, "Clutch" : 0, "Accelerat" : 0, "CarDir" :99.3, "SteelAng" : 540, "ErrContent" : ""},
		{"Index":483, "x" : 191.261, "y" : 22.53, "z" : 0, "Brake" : 0, "Clutch" : 0, "Accelerat" : 0, "CarDir" :99.3, "SteelAng" : 540, "ErrContent" : ""},
		{"Index":484, "x" : 191.261, "y" : 22.53, "z" : 0, "Brake" : 0, "Clutch" : 0, "Accelerat" : 0, "CarDir" :99.3, "SteelAng" : 540, "ErrContent" : ""},
		{"Index":485, "x" : 191.354, "y" : 22.506, "z" : 0, "Brake" : 0, "Clutch" : 0, "Accelerat" : 0, "CarDir" :101.1, "SteelAng" : 540, "ErrContent" : ""},
		{"Index":486, "x" : 191.354, "y" : 22.506, "z" : 0, "Brake" : 0, "Clutch" : 0, "Accelerat" : 0, "CarDir" :101.1, "SteelAng" : 540, "ErrContent" : ""},
		{"Index":487, "x" : 191.354, "y" : 22.506, "z" : 0, "Brake" : 0, "Clutch" : 0, "Accelerat" : 0, "CarDir" :101.1, "SteelAng" : 540, "ErrContent" : ""},
		{"Index":488, "x" : 191.354, "y" : 22.506, "z" : 0, "Brake" : 0, "Clutch" : 0, "Accelerat" : 0, "CarDir" :101.1, "SteelAng" : 540, "ErrContent" : ""},
		{"Index":489, "x" : 191.447, "y" : 22.487, "z" : 0, "Brake" : 0, "Clutch" : 0, "Accelerat" : 0, "CarDir" :102.9, "SteelAng" : 540, "ErrContent" : ""},
		{"Index":490, "x" : 191.447, "y" : 22.487, "z" : 0, "Brake" : 0, "Clutch" : 0, "Accelerat" : 0, "CarDir" :102.9, "SteelAng" : 540, "ErrContent" : ""},
		{"Index":491, "x" : 191.447, "y" : 22.487, "z" : 0, "Brake" : 0, "Clutch" : 0, "Accelerat" : 0, "CarDir" :102.9, "SteelAng" : 540, "ErrContent" : ""},
		{"Index":492, "x" : 191.503, "y" : 22.477, "z" : 0, "Brake" : 0, "Clutch" : 0, "Accelerat" : 0, "CarDir" :103.98, "SteelAng" : 530, "ErrContent" : ""},
		{"Index":493, "x" : 191.521, "y" : 22.474, "z" : 0, "Brake" : 0, "Clutch" : 0, "Accelerat" : 0, "CarDir" :104.33, "SteelAng" : 530, "ErrContent" : ""},
		{"Index":494, "x" : 191.54, "y" : 22.471, "z" : 0, "Brake" : 0, "Clutch" : 0, "Accelerat" : 0, "CarDir" :104.68, "SteelAng" : 530, "ErrContent" : ""},
		{"Index":495, "x" : 191.54, "y" : 22.471, "z" : 0, "Brake" : 0, "Clutch" : 0, "Accelerat" : 0, "CarDir" :104.68, "SteelAng" : 530, "ErrContent" : ""},
		{"Index":496, "x" : 191.54, "y" : 22.471, "z" : 0, "Brake" : 0, "Clutch" : 0, "Accelerat" : 0, "CarDir" :104.68, "SteelAng" : 530, "ErrContent" : ""},
		{"Index":497, "x" : 191.616, "y" : 22.462, "z" : 0, "Brake" : 0, "Clutch" : 0, "Accelerat" : 0, "CarDir" :106.09, "SteelAng" : 530, "ErrContent" : ""},
		{"Index":498, "x" : 191.635, "y" : 22.46, "z" : 0, "Brake" : 0, "Clutch" : 0, "Accelerat" : 0, "CarDir" :106.44, "SteelAng" : 530, "ErrContent" : ""},
		{"Index":499, "x" : 191.635, "y" : 22.46, "z" : 0, "Brake" : 0, "Clutch" : 0, "Accelerat" : 0, "CarDir" :106.44, "SteelAng" : 530, "ErrContent" : ""},
		{"Index":500, "x" : 191.635, "y" : 22.46, "z" : 0, "Brake" : 0, "Clutch" : 0, "Accelerat" : 0, "CarDir" :106.44, "SteelAng" : 530, "ErrContent" : ""},
		{"Index":501, "x" : 191.635, "y" : 22.46, "z" : 0, "Brake" : 0, "Clutch" : 0, "Accelerat" : 0, "CarDir" :106.44, "SteelAng" : 520, "ErrContent" : ""},
		{"Index":502, "x" : 191.711, "y" : 22.453, "z" : 0, "Brake" : 0, "Clutch" : 0, "Accelerat" : 0, "CarDir" :107.83, "SteelAng" : 510, "ErrContent" : ""},
		{"Index":503, "x" : 191.73, "y" : 22.453, "z" : 0, "Brake" : 0, "Clutch" : 0, "Accelerat" : 0, "CarDir" :108.16, "SteelAng" : 490, "ErrContent" : ""},
		{"Index":504, "x" : 191.73, "y" : 22.453, "z" : 0, "Brake" : 0, "Clutch" : 0, "Accelerat" : 0, "CarDir" :108.16, "SteelAng" : 480, "ErrContent" : ""},
		{"Index":505, "x" : 191.73, "y" : 22.453, "z" : 0, "Brake" : 0, "Clutch" : 0, "Accelerat" : 0, "CarDir" :108.16, "SteelAng" : 460, "ErrContent" : ""},
		{"Index":506, "x" : 191.787, "y" : 22.453, "z" : 0, "Brake" : 0, "Clutch" : 0, "Accelerat" : 0, "CarDir" :109.07, "SteelAng" : 460, "ErrContent" : ""},
		{"Index":507, "x" : 191.787, "y" : 22.453, "z" : 0, "Brake" : 0, "Clutch" : 0, "Accelerat" : 0, "CarDir" :109.07, "SteelAng" : 440, "ErrContent" : ""},
		{"Index":508, "x" : 191.787, "y" : 22.453, "z" : 0, "Brake" : 0, "Clutch" : 0, "Accelerat" : 0, "CarDir" :109.07, "SteelAng" : 430, "ErrContent" : ""},
		{"Index":509, "x" : 191.787, "y" : 22.453, "z" : 0, "Brake" : 0, "Clutch" : 0, "Accelerat" : 0, "CarDir" :109.07, "SteelAng" : 420, "ErrContent" : ""},
		{"Index":510, "x" : 191.864, "y" : 22.459, "z" : 0, "Brake" : 0, "Clutch" : 0, "Accelerat" : 0, "CarDir" :110.16, "SteelAng" : 400, "ErrContent" : ""},
		{"Index":511, "x" : 191.864, "y" : 22.459, "z" : 0, "Brake" : 0, "Clutch" : 0, "Accelerat" : 0, "CarDir" :110.16, "SteelAng" : 380, "ErrContent" : ""},
		{"Index":512, "x" : 191.864, "y" : 22.459, "z" : 0, "Brake" : 0, "Clutch" : 0, "Accelerat" : 0, "CarDir" :110.16, "SteelAng" : 360, "ErrContent" : ""},
		{"Index":513, "x" : 191.864, "y" : 22.459, "z" : 0, "Brake" : 0, "Clutch" : 0, "Accelerat" : 0, "CarDir" :110.16, "SteelAng" : 350, "ErrContent" : ""},
		{"Index":514, "x" : 191.98, "y" : 22.48, "z" : 0, "Brake" : 0, "Clutch" : 0, "Accelerat" : 0, "CarDir" :111.45, "SteelAng" : 310, "ErrContent" : ""},
		{"Index":515, "x" : 191.999, "y" : 22.485, "z" : 0, "Brake" : 0, "Clutch" : 0, "Accelerat" : 0, "CarDir" :111.63, "SteelAng" : 300, "ErrContent" : ""},
		{"Index":516, "x" : 192.018, "y" : 22.49, "z" : 0, "Brake" : 0, "Clutch" : 0, "Accelerat" : 0, "CarDir" :111.8, "SteelAng" : 280, "ErrContent" : ""},
		{"Index":517, "x" : 192.038, "y" : 22.495, "z" : 0, "Brake" : 0, "Clutch" : 0, "Accelerat" : 0, "CarDir" :111.96, "SteelAng" : 270, "ErrContent" : ""},
		{"Index":518, "x" : 192.057, "y" : 22.501, "z" : 0, "Brake" : 0, "Clutch" : 0, "Accelerat" : 0, "CarDir" :112.11, "SteelAng" : 260, "ErrContent" : ""},
		{"Index":519, "x" : 192.076, "y" : 22.506, "z" : 0, "Brake" : 0, "Clutch" : 0, "Accelerat" : 0, "CarDir" :112.25, "SteelAng" : 240, "ErrContent" : ""},
		{"Index":520, "x" : 192.076, "y" : 22.506, "z" : 0, "Brake" : 0, "Clutch" : 0, "Accelerat" : 0, "CarDir" :112.25, "SteelAng" : 210, "ErrContent" : ""},
		{"Index":521, "x" : 192.076, "y" : 22.506, "z" : 0, "Brake" : 0, "Clutch" : 0, "Accelerat" : 0, "CarDir" :112.25, "SteelAng" : 210, "ErrContent" : ""},
		{"Index":522, "x" : 192.152, "y" : 22.533, "z" : 0, "Brake" : 0, "Clutch" : 0, "Accelerat" : 0, "CarDir" :112.71, "SteelAng" : 180, "ErrContent" : ""},
		{"Index":523, "x" : 192.152, "y" : 22.533, "z" : 0, "Brake" : 0, "Clutch" : 0, "Accelerat" : 0, "CarDir" :112.71, "SteelAng" : 160, "ErrContent" : ""},
		{"Index":524, "x" : 192.19, "y" : 22.548, "z" : 0, "Brake" : 0, "Clutch" : 0, "Accelerat" : 0, "CarDir" :112.89, "SteelAng" : 150, "ErrContent" : ""},
		{"Index":525, "x" : 192.228, "y" : 22.564, "z" : 0, "Brake" : 0, "Clutch" : 0, "Accelerat" : 0, "CarDir" :113.04, "SteelAng" : 120, "ErrContent" : ""},
		{"Index":526, "x" : 192.246, "y" : 22.572, "z" : 0, "Brake" : 0, "Clutch" : 0, "Accelerat" : 0, "CarDir" :113.1, "SteelAng" : 100, "ErrContent" : ""},
		{"Index":527, "x" : 192.265, "y" : 22.58, "z" : 0, "Brake" : 0, "Clutch" : 0, "Accelerat" : 0, "CarDir" :113.15, "SteelAng" : 90, "ErrContent" : ""},
		{"Index":528, "x" : 192.284, "y" : 22.589, "z" : 0, "Brake" : 0, "Clutch" : 0, "Accelerat" : 0, "CarDir" :113.2, "SteelAng" : 70, "ErrContent" : ""},
		{"Index":529, "x" : 192.302, "y" : 22.598, "z" : 0, "Brake" : 0, "Clutch" : 0, "Accelerat" : 0, "CarDir" :113.23, "SteelAng" : 60, "ErrContent" : ""},
		{"Index":530, "x" : 192.321, "y" : 22.607, "z" : 0, "Brake" : 0, "Clutch" : 0, "Accelerat" : 0, "CarDir" :113.26, "SteelAng" : 40, "ErrContent" : ""},
		{"Index":531, "x" : 192.321, "y" : 22.607, "z" : 0, "Brake" : 0, "Clutch" : 0, "Accelerat" : 0, "CarDir" :113.26, "SteelAng" : 30, "ErrContent" : ""},
		{"Index":532, "x" : 192.376, "y" : 22.635, "z" : 0, "Brake" : 0, "Clutch" : 0, "Accelerat" : 0, "CarDir" :113.3, "SteelAng" : 0, "ErrContent" : ""},
		{"Index":533, "x" : 192.395, "y" : 22.643, "z" : 0, "Brake" : 0, "Clutch" : 0, "Accelerat" : 0, "CarDir" :113.3, "SteelAng" : -20, "ErrContent" : ""},
		{"Index":534, "x" : 192.395, "y" : 22.643, "z" : 0, "Brake" : 0, "Clutch" : 0, "Accelerat" : 0, "CarDir" :113.3, "SteelAng" : -20, "ErrContent" : ""},
		{"Index":535, "x" : 192.432, "y" : 22.663, "z" : 0, "Brake" : 0, "Clutch" : 0, "Accelerat" : 0, "CarDir" :113.28, "SteelAng" : -50, "ErrContent" : ""},
		{"Index":536, "x" : 192.45, "y" : 22.673, "z" : 0, "Brake" : 0, "Clutch" : 0, "Accelerat" : 0, "CarDir" :113.25, "SteelAng" : -60, "ErrContent" : ""},
		{"Index":537, "x" : 192.45, "y" : 22.673, "z" : 0, "Brake" : 0, "Clutch" : 0, "Accelerat" : 0, "CarDir" :113.25, "SteelAng" : -60, "ErrContent" : ""},
		{"Index":538, "x" : 192.468, "y" : 22.683, "z" : 0, "Brake" : 0, "Clutch" : 0, "Accelerat" : 0, "CarDir" :113.22, "SteelAng" : -80, "ErrContent" : ""},
		{"Index":539, "x" : 192.468, "y" : 22.683, "z" : 0, "Brake" : 0, "Clutch" : 0, "Accelerat" : 0, "CarDir" :113.22, "SteelAng" : -110, "ErrContent" : ""},
		{"Index":540, "x" : 192.468, "y" : 22.683, "z" : 0, "Brake" : 0, "Clutch" : 0, "Accelerat" : 0, "CarDir" :113.22, "SteelAng" : -110, "ErrContent" : ""},
		{"Index":541, "x" : 192.468, "y" : 22.683, "z" : 0, "Brake" : 0, "Clutch" : 0, "Accelerat" : 0, "CarDir" :113.22, "SteelAng" : -120, "ErrContent" : ""},
		{"Index":542, "x" : 192.557, "y" : 22.736, "z" : 0, "Brake" : 0, "Clutch" : 0, "Accelerat" : 0, "CarDir" :112.94, "SteelAng" : -150, "ErrContent" : ""},
		{"Index":543, "x" : 192.591, "y" : 22.758, "z" : 0, "Brake" : 0, "Clutch" : 0, "Accelerat" : 0, "CarDir" :112.78, "SteelAng" : -190, "ErrContent" : ""},
		{"Index":544, "x" : 192.591, "y" : 22.758, "z" : 0, "Brake" : 0, "Clutch" : 0, "Accelerat" : 0, "CarDir" :112.78, "SteelAng" : -250, "ErrContent" : ""},
		{"Index":545, "x" : 192.677, "y" : 22.816, "z" : 0, "Brake" : 0, "Clutch" : 0, "Accelerat" : 0, "CarDir" :112.19, "SteelAng" : -260, "ErrContent" : ""},
		{"Index":546, "x" : 192.677, "y" : 22.816, "z" : 0, "Brake" : 0, "Clutch" : 0, "Accelerat" : 0, "CarDir" :112.19, "SteelAng" : -280, "ErrContent" : ""},
		{"Index":547, "x" : 192.677, "y" : 22.816, "z" : 0, "Brake" : 0, "Clutch" : 0, "Accelerat" : 0, "CarDir" :112.19, "SteelAng" : -280, "ErrContent" : ""},
		{"Index":548, "x" : 192.677, "y" : 22.816, "z" : 0, "Brake" : 0, "Clutch" : 0, "Accelerat" : 0, "CarDir" :112.19, "SteelAng" : -290, "ErrContent" : ""},
		{"Index":549, "x" : 192.743, "y" : 22.863, "z" : 0, "Brake" : 0, "Clutch" : 0, "Accelerat" : 0, "CarDir" :111.55, "SteelAng" : -320, "ErrContent" : ""},
		{"Index":550, "x" : 192.743, "y" : 22.863, "z" : 0, "Brake" : 0, "Clutch" : 0, "Accelerat" : 0, "CarDir" :111.55, "SteelAng" : -320, "ErrContent" : ""},
		{"Index":551, "x" : 192.759, "y" : 22.876, "z" : 0, "Brake" : 0, "Clutch" : 0, "Accelerat" : 0, "CarDir" :111.37, "SteelAng" : -340, "ErrContent" : ""},
		{"Index":552, "x" : 192.775, "y" : 22.888, "z" : 0, "Brake" : 0, "Clutch" : 0, "Accelerat" : 0, "CarDir" :111.17, "SteelAng" : -370, "ErrContent" : ""},
		{"Index":553, "x" : 192.775, "y" : 22.888, "z" : 0, "Brake" : 0, "Clutch" : 0, "Accelerat" : 0, "CarDir" :111.17, "SteelAng" : -370, "ErrContent" : ""},
		{"Index":554, "x" : 192.775, "y" : 22.888, "z" : 0, "Brake" : 0, "Clutch" : 0, "Accelerat" : 0, "CarDir" :111.17, "SteelAng" : -380, "ErrContent" : ""},
		{"Index":555, "x" : 192.823, "y" : 22.925, "z" : 0, "Brake" : 0, "Clutch" : 0, "Accelerat" : 0, "CarDir" :110.52, "SteelAng" : -410, "ErrContent" : ""},
		{"Index":556, "x" : 192.854, "y" : 22.951, "z" : 0, "Brake" : 0, "Clutch" : 0, "Accelerat" : 0, "CarDir" :110.03, "SteelAng" : -430, "ErrContent" : ""},
		{"Index":557, "x" : 192.854, "y" : 22.951, "z" : 0, "Brake" : 0, "Clutch" : 0, "Accelerat" : 0, "CarDir" :110.03, "SteelAng" : -440, "ErrContent" : ""},
		{"Index":558, "x" : 192.884, "y" : 22.976, "z" : 0, "Brake" : 0, "Clutch" : 0, "Accelerat" : 0, "CarDir" :109.49, "SteelAng" : -460, "ErrContent" : ""},
		{"Index":559, "x" : 192.884, "y" : 22.976, "z" : 0, "Brake" : 0, "Clutch" : 0, "Accelerat" : 0, "CarDir" :109.49, "SteelAng" : -470, "ErrContent" : ""},
		{"Index":560, "x" : 192.914, "y" : 23.003, "z" : 0, "Brake" : 0, "Clutch" : 0, "Accelerat" : 0, "CarDir" :108.91, "SteelAng" : -490, "ErrContent" : ""},
		{"Index":561, "x" : 192.914, "y" : 23.003, "z" : 0, "Brake" : 0, "Clutch" : 0, "Accelerat" : 0, "CarDir" :108.91, "SteelAng" : -490, "ErrContent" : ""},
		{"Index":562, "x" : 192.929, "y" : 23.016, "z" : 0, "Brake" : 0, "Clutch" : 0, "Accelerat" : 0, "CarDir" :108.59, "SteelAng" : -500, "ErrContent" : ""},
		{"Index":563, "x" : 193.072, "y" : 23.149, "z" : 0, "Brake" : 0, "Clutch" : 0, "Accelerat" : 0, "CarDir" :105.06, "SteelAng" : -540, "ErrContent" : ""},
		{"Index":564, "x" : 193.102, "y" : 23.174, "z" : 0, "Brake" : 0, "Clutch" : 0, "Accelerat" : 0, "CarDir" :104.34, "SteelAng" : -540, "ErrContent" : ""},
		{"Index":565, "x" : 193.102, "y" : 23.174, "z" : 0, "Brake" : 0, "Clutch" : 0, "Accelerat" : 0, "CarDir" :104.34, "SteelAng" : -540, "ErrContent" : ""},
		{"Index":566, "x" : 193.102, "y" : 23.174, "z" : 0, "Brake" : 0, "Clutch" : 0, "Accelerat" : 0, "CarDir" :104.34, "SteelAng" : -540, "ErrContent" : ""},
		{"Index":567, "x" : 193.146, "y" : 23.211, "z" : 0, "Brake" : 0, "Clutch" : 0, "Accelerat" : 0, "CarDir" :103.25, "SteelAng" : -540, "ErrContent" : ""},
		{"Index":568, "x" : 193.161, "y" : 23.223, "z" : 0, "Brake" : 0, "Clutch" : 0, "Accelerat" : 0, "CarDir" :102.89, "SteelAng" : -540, "ErrContent" : ""},
		{"Index":569, "x" : 193.161, "y" : 23.223, "z" : 0, "Brake" : 0, "Clutch" : 0, "Accelerat" : 0, "CarDir" :102.89, "SteelAng" : -540, "ErrContent" : ""},
		{"Index":570, "x" : 193.177, "y" : 23.235, "z" : 0, "Brake" : 0, "Clutch" : 0, "Accelerat" : 0, "CarDir" :102.53, "SteelAng" : -540, "ErrContent" : ""},
		{"Index":571, "x" : 193.192, "y" : 23.247, "z" : 0, "Brake" : 0, "Clutch" : 0, "Accelerat" : 0, "CarDir" :102.17, "SteelAng" : -540, "ErrContent" : ""},
		{"Index":572, "x" : 193.192, "y" : 23.247, "z" : 0, "Brake" : 0, "Clutch" : 0, "Accelerat" : 0, "CarDir" :102.17, "SteelAng" : -540, "ErrContent" : ""},
		{"Index":573, "x" : 193.192, "y" : 23.247, "z" : 0, "Brake" : 0, "Clutch" : 0, "Accelerat" : 0, "CarDir" :102.17, "SteelAng" : -540, "ErrContent" : ""},
		{"Index":574, "x" : 193.192, "y" : 23.247, "z" : 0, "Brake" : 0, "Clutch" : 0, "Accelerat" : 0, "CarDir" :102.17, "SteelAng" : -540, "ErrContent" : ""},
		{"Index":575, "x" : 193.238, "y" : 23.282, "z" : 0, "Brake" : 0, "Clutch" : 0, "Accelerat" : 0, "CarDir" :101.09, "SteelAng" : -540, "ErrContent" : ""},
		{"Index":576, "x" : 193.253, "y" : 23.294, "z" : 0, "Brake" : 0, "Clutch" : 0, "Accelerat" : 0, "CarDir" :100.73, "SteelAng" : -540, "ErrContent" : ""},
		{"Index":577, "x" : 193.253, "y" : 23.294, "z" : 0, "Brake" : 0, "Clutch" : 0, "Accelerat" : 0, "CarDir" :100.73, "SteelAng" : -540, "ErrContent" : ""},
		{"Index":578, "x" : 193.253, "y" : 23.294, "z" : 0, "Brake" : 0, "Clutch" : 0, "Accelerat" : 0, "CarDir" :100.73, "SteelAng" : -540, "ErrContent" : ""},
		{"Index":579, "x" : 193.253, "y" : 23.294, "z" : 0, "Brake" : 0, "Clutch" : 0, "Accelerat" : 0, "CarDir" :100.73, "SteelAng" : -540, "ErrContent" : ""},
		{"Index":580, "x" : 193.269, "y" : 23.305, "z" : 0, "Brake" : 0, "Clutch" : 0, "Accelerat" : 0, "CarDir" :100.37, "SteelAng" : -540, "ErrContent" : ""},
		{"Index":581, "x" : 193.284, "y" : 23.316, "z" : 0, "Brake" : 0, "Clutch" : 0, "Accelerat" : 0, "CarDir" :100.01, "SteelAng" : -540, "ErrContent" : ""},
		{"Index":582, "x" : 193.3, "y" : 23.327, "z" : 0, "Brake" : 0, "Clutch" : 0, "Accelerat" : 0, "CarDir" :99.65, "SteelAng" : -540, "ErrContent" : ""},
		{"Index":583, "x" : 193.3, "y" : 23.327, "z" : 0, "Brake" : 0, "Clutch" : 0, "Accelerat" : 0, "CarDir" :99.65, "SteelAng" : -540, "ErrContent" : ""},
		{"Index":584, "x" : 193.3, "y" : 23.327, "z" : 0, "Brake" : 0, "Clutch" : 0, "Accelerat" : 0, "CarDir" :99.65, "SteelAng" : -540, "ErrContent" : ""},
		{"Index":585, "x" : 193.3, "y" : 23.327, "z" : 0, "Brake" : 0, "Clutch" : 0, "Accelerat" : 0, "CarDir" :99.65, "SteelAng" : -540, "ErrContent" : ""},
		{"Index":586, "x" : 193.3, "y" : 23.327, "z" : 0, "Brake" : 0, "Clutch" : 0, "Accelerat" : 0, "CarDir" :99.65, "SteelAng" : -540, "ErrContent" : ""},
		{"Index":587, "x" : 193.3, "y" : 23.327, "z" : 0, "Brake" : 0, "Clutch" : 0, "Accelerat" : 0, "CarDir" :99.65, "SteelAng" : -540, "ErrContent" : ""},
		{"Index":588, "x" : 193.3, "y" : 23.327, "z" : 0, "Brake" : 0, "Clutch" : 0, "Accelerat" : 0, "CarDir" :99.65, "SteelAng" : -540, "ErrContent" : ""},
		{"Index":589, "x" : 193.3, "y" : 23.327, "z" : 0, "Brake" : 0, "Clutch" : 0, "Accelerat" : 0, "CarDir" :99.65, "SteelAng" : -540, "ErrContent" : ""},
		{"Index":590, "x" : 193.3, "y" : 23.327, "z" : 0, "Brake" : 0, "Clutch" : 0, "Accelerat" : 0, "CarDir" :99.65, "SteelAng" : -540, "ErrContent" : ""},
		{"Index":591, "x" : 193.3, "y" : 23.327, "z" : 0, "Brake" : 0, "Clutch" : 0, "Accelerat" : 0, "CarDir" :99.65, "SteelAng" : -540, "ErrContent" : ""},
		{"Index":592, "x" : 193.3, "y" : 23.327, "z" : 0, "Brake" : 0, "Clutch" : 0, "Accelerat" : 0, "CarDir" :99.65, "SteelAng" : -540, "ErrContent" : ""},
		{"Index":593, "x" : 193.3, "y" : 23.327, "z" : 0, "Brake" : 0, "Clutch" : 0, "Accelerat" : 0, "CarDir" :99.65, "SteelAng" : -540, "ErrContent" : ""},
		{"Index":594, "x" : 193.3, "y" : 23.327, "z" : 0, "Brake" : 0, "Clutch" : 0, "Accelerat" : 0, "CarDir" :99.65, "SteelAng" : -540, "ErrContent" : ""},
		{"Index":595, "x" : 193.3, "y" : 23.327, "z" : 0, "Brake" : 0, "Clutch" : 0, "Accelerat" : 0, "CarDir" :99.65, "SteelAng" : -540, "ErrContent" : ""},
		{"Index":596, "x" : 193.3, "y" : 23.327, "z" : 0, "Brake" : 0, "Clutch" : 0, "Accelerat" : 0, "CarDir" :99.65, "SteelAng" : -540, "ErrContent" : ""},
		{"Index":597, "x" : 193.3, "y" : 23.327, "z" : 0, "Brake" : 0, "Clutch" : 0, "Accelerat" : 0, "CarDir" :99.65, "SteelAng" : -540, "ErrContent" : ""},
		{"Index":598, "x" : 193.3, "y" : 23.327, "z" : 0, "Brake" : 0, "Clutch" : 0, "Accelerat" : 0, "CarDir" :99.65, "SteelAng" : -540, "ErrContent" : ""},
		{"Index":599, "x" : 193.3, "y" : 23.327, "z" : 0, "Brake" : 0, "Clutch" : 0, "Accelerat" : 0, "CarDir" :99.65, "SteelAng" : -540, "ErrContent" : ""},
		{"Index":600, "x" : 193.3, "y" : 23.327, "z" : 0, "Brake" : 0, "Clutch" : 0, "Accelerat" : 0, "CarDir" :99.65, "SteelAng" : -540, "ErrContent" : ""},
		{"Index":601, "x" : 193.3, "y" : 23.327, "z" : 0, "Brake" : 0, "Clutch" : 0, "Accelerat" : 0, "CarDir" :99.65, "SteelAng" : -540, "ErrContent" : ""},
		{"Index":602, "x" : 193.3, "y" : 23.327, "z" : 0, "Brake" : 0, "Clutch" : 0, "Accelerat" : 0, "CarDir" :99.65, "SteelAng" : -540, "ErrContent" : ""},
		{"Index":603, "x" : 193.3, "y" : 23.327, "z" : 0, "Brake" : 0, "Clutch" : 0, "Accelerat" : 0, "CarDir" :99.65, "SteelAng" : -540, "ErrContent" : ""},
		{"Index":604, "x" : 193.3, "y" : 23.327, "z" : 0, "Brake" : 0, "Clutch" : 0, "Accelerat" : 0, "CarDir" :99.65, "SteelAng" : -540, "ErrContent" : ""},
		{"Index":605, "x" : 193.3, "y" : 23.327, "z" : 0, "Brake" : 0, "Clutch" : 0, "Accelerat" : 0, "CarDir" :99.65, "SteelAng" : -540, "ErrContent" : ""},
		{"Index":606, "x" : 193.3, "y" : 23.327, "z" : 0, "Brake" : 0, "Clutch" : 0, "Accelerat" : 0, "CarDir" :99.65, "SteelAng" : -540, "ErrContent" : ""},
		{"Index":607, "x" : 193.3, "y" : 23.327, "z" : 0, "Brake" : 0, "Clutch" : 0, "Accelerat" : 0, "CarDir" :99.65, "SteelAng" : -540, "ErrContent" : ""},
		{"Index":608, "x" : 193.3, "y" : 23.327, "z" : 0, "Brake" : 0, "Clutch" : 0, "Accelerat" : 0, "CarDir" :99.65, "SteelAng" : -540, "ErrContent" : ""},
		{"Index":609, "x" : 193.3, "y" : 23.327, "z" : 0, "Brake" : 0, "Clutch" : 0, "Accelerat" : 0, "CarDir" :99.65, "SteelAng" : -540, "ErrContent" : ""},
		{"Index":610, "x" : 193.3, "y" : 23.327, "z" : 0, "Brake" : 0, "Clutch" : 0, "Accelerat" : 0, "CarDir" :99.65, "SteelAng" : -540, "ErrContent" : ""},
		{"Index":611, "x" : 193.3, "y" : 23.327, "z" : 0, "Brake" : 0, "Clutch" : 0, "Accelerat" : 0, "CarDir" :99.65, "SteelAng" : -540, "ErrContent" : ""},
		{"Index":612, "x" : 193.3, "y" : 23.327, "z" : 0, "Brake" : 0, "Clutch" : 0, "Accelerat" : 0, "CarDir" :99.65, "SteelAng" : -540, "ErrContent" : ""},
		{"Index":613, "x" : 193.3, "y" : 23.327, "z" : 0, "Brake" : 0, "Clutch" : 0, "Accelerat" : 0, "CarDir" :99.65, "SteelAng" : -540, "ErrContent" : ""},
		{"Index":614, "x" : 193.3, "y" : 23.327, "z" : 0, "Brake" : 0, "Clutch" : 0, "Accelerat" : 0, "CarDir" :99.65, "SteelAng" : -540, "ErrContent" : ""},
		{"Index":615, "x" : 193.3, "y" : 23.327, "z" : 0, "Brake" : 0, "Clutch" : 0, "Accelerat" : 0, "CarDir" :99.65, "SteelAng" : -540, "ErrContent" : ""},
		{"Index":616, "x" : 193.3, "y" : 23.327, "z" : 0, "Brake" : 0, "Clutch" : 0, "Accelerat" : 0, "CarDir" :99.65, "SteelAng" : -540, "ErrContent" : ""},
		{"Index":617, "x" : 193.3, "y" : 23.327, "z" : 0, "Brake" : 0, "Clutch" : 0, "Accelerat" : 0, "CarDir" :99.65, "SteelAng" : -540, "ErrContent" : ""},
		{"Index":618, "x" : 193.3, "y" : 23.327, "z" : 0, "Brake" : 0, "Clutch" : 0, "Accelerat" : 0, "CarDir" :99.65, "SteelAng" : -540, "ErrContent" : ""},
		{"Index":619, "x" : 193.3, "y" : 23.327, "z" : 0, "Brake" : 0, "Clutch" : 0, "Accelerat" : 0, "CarDir" :99.65, "SteelAng" : -540, "ErrContent" : ""},
		{"Index":620, "x" : 193.3, "y" : 23.327, "z" : 0, "Brake" : 0, "Clutch" : 0, "Accelerat" : 0, "CarDir" :99.65, "SteelAng" : -540, "ErrContent" : ""},
		{"Index":621, "x" : 193.3, "y" : 23.327, "z" : 0, "Brake" : 0, "Clutch" : 0, "Accelerat" : 0, "CarDir" :99.65, "SteelAng" : -540, "ErrContent" : ""},
		{"Index":622, "x" : 193.3, "y" : 23.327, "z" : 0, "Brake" : 0, "Clutch" : 0, "Accelerat" : 0, "CarDir" :99.65, "SteelAng" : -540, "ErrContent" : ""},
		{"Index":623, "x" : 193.3, "y" : 23.327, "z" : 0, "Brake" : 0, "Clutch" : 0, "Accelerat" : 0, "CarDir" :99.65, "SteelAng" : -540, "ErrContent" : ""},
		{"Index":624, "x" : 193.3, "y" : 23.327, "z" : 0, "Brake" : 0, "Clutch" : 0, "Accelerat" : 0, "CarDir" :99.65, "SteelAng" : -540, "ErrContent" : ""},
		{"Index":625, "x" : 193.3, "y" : 23.327, "z" : 0, "Brake" : 0, "Clutch" : 0, "Accelerat" : 0, "CarDir" :99.65, "SteelAng" : -540, "ErrContent" : ""},
		{"Index":626, "x" : 193.3, "y" : 23.327, "z" : 0, "Brake" : 0, "Clutch" : 0, "Accelerat" : 0, "CarDir" :99.65, "SteelAng" : -540, "ErrContent" : ""},
		{"Index":627, "x" : 193.3, "y" : 23.327, "z" : 0, "Brake" : 0, "Clutch" : 0, "Accelerat" : 0, "CarDir" :99.65, "SteelAng" : -540, "ErrContent" : ""},
		{"Index":628, "x" : 193.3, "y" : 23.327, "z" : 0, "Brake" : 0, "Clutch" : 0, "Accelerat" : 0, "CarDir" :99.65, "SteelAng" : -540, "ErrContent" : ""},
		{"Index":629, "x" : 193.3, "y" : 23.327, "z" : 0, "Brake" : 0, "Clutch" : 0, "Accelerat" : 0, "CarDir" :99.65, "SteelAng" : -540, "ErrContent" : ""},
		{"Index":630, "x" : 193.3, "y" : 23.327, "z" : 0, "Brake" : 0, "Clutch" : 0, "Accelerat" : 0, "CarDir" :99.65, "SteelAng" : -540, "ErrContent" : ""},
		{"Index":631, "x" : 193.3, "y" : 23.327, "z" : 0, "Brake" : 0, "Clutch" : 0, "Accelerat" : 0, "CarDir" :99.65, "SteelAng" : -540, "ErrContent" : ""},
		{"Index":632, "x" : 193.3, "y" : 23.327, "z" : 0, "Brake" : 0, "Clutch" : 0, "Accelerat" : 0, "CarDir" :99.65, "SteelAng" : -540, "ErrContent" : ""},
		{"Index":633, "x" : 193.3, "y" : 23.327, "z" : 0, "Brake" : 0, "Clutch" : 0, "Accelerat" : 0, "CarDir" :99.65, "SteelAng" : -540, "ErrContent" : ""},
		{"Index":634, "x" : 193.3, "y" : 23.327, "z" : 0, "Brake" : 0, "Clutch" : 0, "Accelerat" : 0, "CarDir" :99.65, "SteelAng" : -540, "ErrContent" : ""},
		{"Index":635, "x" : 193.3, "y" : 23.327, "z" : 0, "Brake" : 0, "Clutch" : 0, "Accelerat" : 0, "CarDir" :99.65, "SteelAng" : -540, "ErrContent" : ""},
		{"Index":636, "x" : 193.3, "y" : 23.327, "z" : 0, "Brake" : 0, "Clutch" : 0, "Accelerat" : 0, "CarDir" :99.65, "SteelAng" : -540, "ErrContent" : ""},
		{"Index":637, "x" : 193.3, "y" : 23.327, "z" : 0, "Brake" : 0, "Clutch" : 0, "Accelerat" : 0, "CarDir" :99.65, "SteelAng" : -540, "ErrContent" : ""},
		{"Index":638, "x" : 193.3, "y" : 23.327, "z" : 0, "Brake" : 0, "Clutch" : 0, "Accelerat" : 0, "CarDir" :99.65, "SteelAng" : -540, "ErrContent" : ""},
		{"Index":639, "x" : 193.3, "y" : 23.327, "z" : 0, "Brake" : 0, "Clutch" : 0, "Accelerat" : 0, "CarDir" :99.65, "SteelAng" : -540, "ErrContent" : ""},
		{"Index":640, "x" : 193.3, "y" : 23.327, "z" : 0, "Brake" : 0, "Clutch" : 0, "Accelerat" : 0, "CarDir" :99.65, "SteelAng" : -540, "ErrContent" : ""},
		{"Index":641, "x" : 193.3, "y" : 23.327, "z" : 0, "Brake" : 0, "Clutch" : 0, "Accelerat" : 0, "CarDir" :99.65, "SteelAng" : -540, "ErrContent" : ""},
		{"Index":642, "x" : 193.3, "y" : 23.327, "z" : 0, "Brake" : 0, "Clutch" : 0, "Accelerat" : 0, "CarDir" :99.65, "SteelAng" : -540, "ErrContent" : ""},
		{"Index":643, "x" : 193.3, "y" : 23.327, "z" : 0, "Brake" : 0, "Clutch" : 0, "Accelerat" : 0, "CarDir" :99.65, "SteelAng" : -540, "ErrContent" : ""},
		{"Index":644, "x" : 193.3, "y" : 23.327, "z" : 0, "Brake" : 0, "Clutch" : 0, "Accelerat" : 0, "CarDir" :99.65, "SteelAng" : -540, "ErrContent" : ""},
		{"Index":645, "x" : 193.3, "y" : 23.327, "z" : 0, "Brake" : 0, "Clutch" : 0, "Accelerat" : 0, "CarDir" :99.65, "SteelAng" : -540, "ErrContent" : ""},
		{"Index":646, "x" : 193.3, "y" : 23.327, "z" : 0, "Brake" : 0, "Clutch" : 0, "Accelerat" : 0, "CarDir" :99.65, "SteelAng" : -540, "ErrContent" : ""}
	]
}